{"ok":true,"slug":"movies/586384","url":"https://krx18.com/movies/586384/","ts":1784803458245,"title":"Alt Girl Plays With Her Ass After A Long Day At College","poster":"https://cdnupload.com/wp-content/uploads/2026/07/poster_KRX.586384_5435.jpg","year":"","genres":["Eng Sub","X Clip","Korea","Australia","Belgium","Canada","China","Denmark","France","Germany","Indonesia","India","Italy","Japan","Netherlands","Philippines","Poland","Russia","Singapore","Spain","Switzerland","Taiwan","Thailand","UK","USA","Anal","Exclusive","Feet","Masturbation","XXX"],"storyline":"","downloads":[],"streams":[]}