{"ok":true,"page":26,"items":[{"slug":"lucifer-UQASHYbVPB2?id=2190807691784770592","title":"Lucifer","poster":"https://pbcdnw.aoneroom.com/image/2026/01/27/9fd9113b6be06b254bef10a8bea06eb1.jpg","year":"2016","quality":"HD","language":"","rating":"8.0","type":"tv"},{"slug":"squid-game-4CyZm1LfdG3?id=3089349649006742360","title":"Squid Game","poster":"https://pbcdnw.aoneroom.com/image/2026/07/19/8735049cc1251e60ae3fadfac6e5ac16.jpg","year":"2021","quality":"HD","language":"","rating":"7.9","type":"tv"},{"slug":"the-boys-c8bx84KzD76?id=5139196938264400928","title":"The Boys","poster":"https://pbcdnw.aoneroom.com/image/2026/06/26/350a107306ba455f1053aea4e032f6b4.jpg","year":"2019","quality":"HD","language":"","rating":"8.5","type":"tv"},{"slug":"the-witcher-qdCxXLAl8y4?id=3819281169544270880","title":"The Witcher","poster":"https://pbcdnw.aoneroom.com/image/2026/07/03/640b4ac5896555b11a8b56a016132a63.jpg","year":"2019","quality":"HD","language":"","rating":"7.8","type":"tv"},{"slug":"goat-u1jZhR4CnV4?id=4133967316415663152","title":"GOAT","poster":"https://pbcdnw.aoneroom.com/image/2026/07/20/92fb928466e840f38d329283cf53adf9.jpg","year":"2026","quality":"HD","language":"","rating":"6.7","type":"movie"},{"slug":"ginny-and-georgia-KHAfHuS4M12?id=1702633325145248800","title":"Ginny & Georgia","poster":"https://pbcdnw.aoneroom.com/image/2026/01/26/946751160c6c4988e51fa237adb2eef2.jpg","year":"2021","quality":"HD","language":"","rating":"7.5","type":"tv"},{"slug":"the-night-agent-QmKtaMxB3N5?id=4860601308702802872","title":"The Night Agent","poster":"https://pbcdnw.aoneroom.com/image/2026/07/22/0cbd6b9b8ad2151d44369ef38f98dad3.jpg","year":"2023","quality":"HD","language":"","rating":"7.4","type":"tv"},{"slug":"the-furious-6lxRH1LLAe5?id=4394044471852286152","title":"The Furious","poster":"https://pbcdnw.aoneroom.com/image/2026/07/21/127385441141dc4f99e301a13b76a9c4.jpg","year":"2026","quality":"HD","language":"","rating":"7.4","type":"movie"},{"slug":"the-summer-i-turned-pretty-qBSaCpLbiJ?id=613140447321543448","title":"The Summer I Turned Pretty","poster":"https://pbcdnw.aoneroom.com/image/2026/01/26/ddc61cd3c81481181c934598cf396662.jpg","year":"2022","quality":"HD","language":"","rating":"7.3","type":"tv"},{"slug":"bridgerton-E4I97hZMhIa?id=8992509766509417240","title":"Bridgerton","poster":"https://pbcdnw.aoneroom.com/image/2026/07/23/c8bd1e666a1cc1887ea6bd0a3be1bcbc.jpg","year":"2020","quality":"HD","language":"","rating":"7.5","type":"tv"},{"slug":"blood-and-water-cU5YJ2fQzD6?id=5571568452684370976","title":"Blood & Water","poster":"https://pbcdnw.aoneroom.com/image/2026/01/26/03c5f69d17e8e96e58ba378aaef8ee14.jpg","year":"2020","quality":"HD","language":"","rating":"6.7","type":"tv"},{"slug":"one-piece-netflix-qL3bmkP9Rr1?id=1216407338207298384","title":"One Piece [netflix]","poster":"https://pbcdnw.aoneroom.com/image/2026/01/26/34ae35dac2710074be44f06842b8ac86.jpg","year":"2023","quality":"HD","language":"","rating":"8.3","type":"tv"},{"slug":"the-lord-of-the-rings-the-rings-of-power-oWxADnOpP26?id=5074096615720375064","title":"The Lord of the Rings: The Rings of Power","poster":"https://pbcdnw.aoneroom.com/image/2026/07/22/9547005fad6c7bfdae0734b146bd1c1d.jpg","year":"2022","quality":"HD","language":"","rating":"6.8","type":"tv"},{"slug":"emily-in-paris-mJBrEblqXY9?id=8378894317280187160","title":"Emily in Paris","poster":"https://pbcdnw.aoneroom.com/image/2026/07/20/669b57c37007d15606553b31bb0aebe2.jpg","year":"2020","quality":"HD","language":"","rating":"6.8","type":"tv"},{"slug":"whats-wrong-with-secretary-kim-SVDUS3jX2n3?id=2829896626406315040","title":"What's Wrong with Secretary Kim","poster":"https://pbcdnw.aoneroom.com/image/2026/01/26/9ab209727cab470cdcafe63300efbfd2.jpg","year":"2018","quality":"HD","language":"","rating":"8.0","type":"tv"},{"slug":"the-uncanny-counter-8MI0xDCdyT9?id=8305705592065248392","title":"The Uncanny Counter","poster":"https://pbcdnw.aoneroom.com/image/2026/01/26/15bfb65ca7a3bf271d97e2c24a0b84f0.jpg","year":"2020","quality":"HD","language":"","rating":"8.0","type":"tv"},{"slug":"king-the-land-23DiL8CfIy3?id=2987820995479752632","title":"King the Land","poster":"https://pbcdnw.aoneroom.com/image/2026/01/26/a768ca27dc67c70a90e5bd845f681d52.jpg","year":"2023","quality":"HD","language":"","rating":"5.8","type":"tv"},{"slug":"supacell-w6597vlyg27?id=5905784132067542064","title":"Supacell","poster":"https://pbcdnw.aoneroom.com/image/2026/07/19/1121d1221783792d530205d0e57abf9b.jpg","year":"2024","quality":"HD","language":"","rating":"7.0","type":"tv"},{"slug":"its-okay-to-not-be-okay-aN4nmaFyGF5?id=4760809735371250080","title":"It's Okay to Not Be Okay","poster":"https://pbcdnw.aoneroom.com/image/2026/01/26/076568c833ec00673e4cf5ebc11dcb8e.jpg","year":"2020","quality":"HD","language":"","rating":"8.6","type":"tv"},{"slug":"when-destiny-brings-the-demon-e78rpL3gys2?id=2065117278290470008","title":"When Destiny Brings the Demon","poster":"https://pbcdnw.aoneroom.com/image/2026/07/22/ffe6ed4115aabf864c4609c52ae28050.jpg","year":"2025","quality":"HD","language":"","rating":"7.8","type":"tv"},{"slug":"p-valley-CHaGLAbLIa7?id=6020239565561156376","title":"P-Valley","poster":"https://pbcdnw.aoneroom.com/image/2026/01/26/e6a6a0cb4393d4520dd07e710bd3b537.jpg","year":"2020","quality":"HD","language":"","rating":"7.5","type":"tv"},{"slug":"hes-into-her-8yTSQrmwKz9?id=8037649933580812240","title":"He's Into Her","poster":"https://pbcdnw.aoneroom.com/image/2026/01/26/429f7ebd29742cf7856ea39a7e1ff0e1.jpg","year":"2021","quality":"HD","language":"","rating":"7.5","type":"tv"},{"slug":"bet-WfZpaLvJaS2?id=2411945082967543816","title":"Bet","poster":"https://pbcdnw.aoneroom.com/image/2026/07/22/56607a0fef52d9507001747a23e40b7b.jpg","year":"2025","quality":"HD","language":"","rating":"6.5","type":"tv"},{"slug":"fated-hearts-ks7tBLGmHo8?id=7048753533340336384","title":"Fated Hearts","poster":"https://pbcdnw.aoneroom.com/image/2026/01/26/1829b3a9b59f9632a451d0002867bd60.jpg","year":"2025","quality":"HD","language":"","rating":"8.3","type":"tv"}],"movies":[{"slug":"lucifer-UQASHYbVPB2?id=2190807691784770592","title":"Lucifer","poster":"https://pbcdnw.aoneroom.com/image/2026/01/27/9fd9113b6be06b254bef10a8bea06eb1.jpg","year":"2016","quality":"HD","language":"","rating":"8.0","type":"tv"},{"slug":"squid-game-4CyZm1LfdG3?id=3089349649006742360","title":"Squid Game","poster":"https://pbcdnw.aoneroom.com/image/2026/07/19/8735049cc1251e60ae3fadfac6e5ac16.jpg","year":"2021","quality":"HD","language":"","rating":"7.9","type":"tv"},{"slug":"the-boys-c8bx84KzD76?id=5139196938264400928","title":"The Boys","poster":"https://pbcdnw.aoneroom.com/image/2026/06/26/350a107306ba455f1053aea4e032f6b4.jpg","year":"2019","quality":"HD","language":"","rating":"8.5","type":"tv"},{"slug":"the-witcher-qdCxXLAl8y4?id=3819281169544270880","title":"The Witcher","poster":"https://pbcdnw.aoneroom.com/image/2026/07/03/640b4ac5896555b11a8b56a016132a63.jpg","year":"2019","quality":"HD","language":"","rating":"7.8","type":"tv"},{"slug":"goat-u1jZhR4CnV4?id=4133967316415663152","title":"GOAT","poster":"https://pbcdnw.aoneroom.com/image/2026/07/20/92fb928466e840f38d329283cf53adf9.jpg","year":"2026","quality":"HD","language":"","rating":"6.7","type":"movie"},{"slug":"ginny-and-georgia-KHAfHuS4M12?id=1702633325145248800","title":"Ginny & Georgia","poster":"https://pbcdnw.aoneroom.com/image/2026/01/26/946751160c6c4988e51fa237adb2eef2.jpg","year":"2021","quality":"HD","language":"","rating":"7.5","type":"tv"},{"slug":"the-night-agent-QmKtaMxB3N5?id=4860601308702802872","title":"The Night Agent","poster":"https://pbcdnw.aoneroom.com/image/2026/07/22/0cbd6b9b8ad2151d44369ef38f98dad3.jpg","year":"2023","quality":"HD","language":"","rating":"7.4","type":"tv"},{"slug":"the-furious-6lxRH1LLAe5?id=4394044471852286152","title":"The Furious","poster":"https://pbcdnw.aoneroom.com/image/2026/07/21/127385441141dc4f99e301a13b76a9c4.jpg","year":"2026","quality":"HD","language":"","rating":"7.4","type":"movie"},{"slug":"the-summer-i-turned-pretty-qBSaCpLbiJ?id=613140447321543448","title":"The Summer I Turned Pretty","poster":"https://pbcdnw.aoneroom.com/image/2026/01/26/ddc61cd3c81481181c934598cf396662.jpg","year":"2022","quality":"HD","language":"","rating":"7.3","type":"tv"},{"slug":"bridgerton-E4I97hZMhIa?id=8992509766509417240","title":"Bridgerton","poster":"https://pbcdnw.aoneroom.com/image/2026/07/23/c8bd1e666a1cc1887ea6bd0a3be1bcbc.jpg","year":"2020","quality":"HD","language":"","rating":"7.5","type":"tv"},{"slug":"blood-and-water-cU5YJ2fQzD6?id=5571568452684370976","title":"Blood & Water","poster":"https://pbcdnw.aoneroom.com/image/2026/01/26/03c5f69d17e8e96e58ba378aaef8ee14.jpg","year":"2020","quality":"HD","language":"","rating":"6.7","type":"tv"},{"slug":"one-piece-netflix-qL3bmkP9Rr1?id=1216407338207298384","title":"One Piece [netflix]","poster":"https://pbcdnw.aoneroom.com/image/2026/01/26/34ae35dac2710074be44f06842b8ac86.jpg","year":"2023","quality":"HD","language":"","rating":"8.3","type":"tv"},{"slug":"the-lord-of-the-rings-the-rings-of-power-oWxADnOpP26?id=5074096615720375064","title":"The Lord of the Rings: The Rings of Power","poster":"https://pbcdnw.aoneroom.com/image/2026/07/22/9547005fad6c7bfdae0734b146bd1c1d.jpg","year":"2022","quality":"HD","language":"","rating":"6.8","type":"tv"},{"slug":"emily-in-paris-mJBrEblqXY9?id=8378894317280187160","title":"Emily in Paris","poster":"https://pbcdnw.aoneroom.com/image/2026/07/20/669b57c37007d15606553b31bb0aebe2.jpg","year":"2020","quality":"HD","language":"","rating":"6.8","type":"tv"},{"slug":"whats-wrong-with-secretary-kim-SVDUS3jX2n3?id=2829896626406315040","title":"What's Wrong with Secretary Kim","poster":"https://pbcdnw.aoneroom.com/image/2026/01/26/9ab209727cab470cdcafe63300efbfd2.jpg","year":"2018","quality":"HD","language":"","rating":"8.0","type":"tv"},{"slug":"the-uncanny-counter-8MI0xDCdyT9?id=8305705592065248392","title":"The Uncanny Counter","poster":"https://pbcdnw.aoneroom.com/image/2026/01/26/15bfb65ca7a3bf271d97e2c24a0b84f0.jpg","year":"2020","quality":"HD","language":"","rating":"8.0","type":"tv"},{"slug":"king-the-land-23DiL8CfIy3?id=2987820995479752632","title":"King the Land","poster":"https://pbcdnw.aoneroom.com/image/2026/01/26/a768ca27dc67c70a90e5bd845f681d52.jpg","year":"2023","quality":"HD","language":"","rating":"5.8","type":"tv"},{"slug":"supacell-w6597vlyg27?id=5905784132067542064","title":"Supacell","poster":"https://pbcdnw.aoneroom.com/image/2026/07/19/1121d1221783792d530205d0e57abf9b.jpg","year":"2024","quality":"HD","language":"","rating":"7.0","type":"tv"},{"slug":"its-okay-to-not-be-okay-aN4nmaFyGF5?id=4760809735371250080","title":"It's Okay to Not Be Okay","poster":"https://pbcdnw.aoneroom.com/image/2026/01/26/076568c833ec00673e4cf5ebc11dcb8e.jpg","year":"2020","quality":"HD","language":"","rating":"8.6","type":"tv"},{"slug":"when-destiny-brings-the-demon-e78rpL3gys2?id=2065117278290470008","title":"When Destiny Brings the Demon","poster":"https://pbcdnw.aoneroom.com/image/2026/07/22/ffe6ed4115aabf864c4609c52ae28050.jpg","year":"2025","quality":"HD","language":"","rating":"7.8","type":"tv"},{"slug":"p-valley-CHaGLAbLIa7?id=6020239565561156376","title":"P-Valley","poster":"https://pbcdnw.aoneroom.com/image/2026/01/26/e6a6a0cb4393d4520dd07e710bd3b537.jpg","year":"2020","quality":"HD","language":"","rating":"7.5","type":"tv"},{"slug":"hes-into-her-8yTSQrmwKz9?id=8037649933580812240","title":"He's Into Her","poster":"https://pbcdnw.aoneroom.com/image/2026/01/26/429f7ebd29742cf7856ea39a7e1ff0e1.jpg","year":"2021","quality":"HD","language":"","rating":"7.5","type":"tv"},{"slug":"bet-WfZpaLvJaS2?id=2411945082967543816","title":"Bet","poster":"https://pbcdnw.aoneroom.com/image/2026/07/22/56607a0fef52d9507001747a23e40b7b.jpg","year":"2025","quality":"HD","language":"","rating":"6.5","type":"tv"},{"slug":"fated-hearts-ks7tBLGmHo8?id=7048753533340336384","title":"Fated Hearts","poster":"https://pbcdnw.aoneroom.com/image/2026/01/26/1829b3a9b59f9632a451d0002867bd60.jpg","year":"2025","quality":"HD","language":"","rating":"8.3","type":"tv"}],"hasMore":true,"source":"moviebox","ts":1784787949725}