{"ok":true,"slug":"bruce-bruce-i-aint-playin-2026-4k-web-english-full-movie","url":"https://hdhub4us.ai.in/bruce-bruce-i-aint-playin-2026-4k-web-english-full-movie/","title":"Bruce Bruce I Ain’t Playin’ (2026) 4K WEB English Full Movie - Hdhub4u","poster":"https://hdhub4us.ai.in/wp-content/uploads/2026/05/Bruce-Bruce-I-Aint-Playin-2026.webp","year":"2026","storyline":"Download Bruce Bruce: I Ain’t Playin’ (2026) English Full Movie and available in 720p 1080p 2160p . This movie is based on Comedy and available in English.","genres":[],"qualities":[],"language":"Hindi Dubbed","downloads":[],"streams":[],"ts":1784840570456}