{"ok":true,"slug":"lingam-season-1-jiohotstar-hindi-dd5-1-tamil-dd5-1-complete-web-series-480p-720p-1080p","url":"https://hdhub4us.ai.in/lingam-season-1-jiohotstar-hindi-dd5-1-tamil-dd5-1-complete-web-series-480p-720p-1080p/","title":"Lingam (Season 1) JioHotstar {Hindi DD5.1 – Tamil DD5.1} Complete Web Series 480p | 720p | 1080p - Hdhub4u","poster":"https://hdhub4us.ai.in/wp-content/uploads/2026/06/tqO8IY6V9T8HNG4mefxPfyLzRpW.webp","year":"","storyline":"At Hdhub4u , dive into the world of High-Speed Hollywood and Bollywood movie downloads with hassle-free, direct Google Drive (G-Drive) links.","genres":[],"qualities":[],"language":"Hindi Dubbed","downloads":[{"label":"480P Direct","url":"https://fastdl.zip/embed.php?download=Y7GUpKgbiHjYTLVXtFOXXnI5D","quality":"480p","size":"150MB","host":"FastDL","isDirect":true,"via":"hdhub.boats"},{"label":"480P Direct","url":"https://filebee.xyz/file/6a3db58c86d6cba55467e0c6","quality":"480p","size":"150MB","host":"FileBee","isDirect":true,"via":"hdhub.boats"},{"label":"480P Direct","url":"https://fastdl.zip/embed.php?download=tEd7W8DvRCI8v5SXXB4ASKOni","quality":"480p","size":"150MB","host":"FastDL","isDirect":true,"via":"hdhub.boats"},{"label":"480P Direct","url":"https://filebee.xyz/file/6a3db5a586d6cba55467e1fb","quality":"480p","size":"150MB","host":"FileBee","isDirect":true,"via":"hdhub.boats"},{"label":"480P Direct","url":"https://fastdl.zip/embed.php?download=30PqCEV7C8UHCjkFjiCWUJs0n","quality":"480p","size":"150MB","host":"FastDL","isDirect":true,"via":"hdhub.boats"},{"label":"480P Direct","url":"https://filebee.xyz/file/6a3db5b886d6cba55467e2fd","quality":"480p","size":"150MB","host":"FileBee","isDirect":true,"via":"hdhub.boats"},{"label":"480P Direct","url":"https://fastdl.zip/embed.php?download=U4CWyFtxWT23iNOyzvb6gNEaE","quality":"480p","size":"150MB","host":"FastDL","isDirect":true,"via":"hdhub.boats"},{"label":"480P Direct","url":"https://filebee.xyz/file/6a3db5ce86d6cba55467e49f","quality":"480p","size":"150MB","host":"FileBee","isDirect":true,"via":"hdhub.boats"},{"label":"480P Direct","url":"https://fastdl.zip/embed.php?download=CvAb1oLLn2rtgfxtdYZMLHjAO","quality":"480p","size":"150MB","host":"FastDL","isDirect":true,"via":"hdhub.boats"},{"label":"480P Direct","url":"https://filebee.xyz/file/6a3db5e786d6cba55467e608","quality":"480p","size":"150MB","host":"FileBee","isDirect":true,"via":"hdhub.boats"},{"label":"480P Direct","url":"https://fastdl.zip/embed.php?download=j6Hftq5B7ivnrYfwMf2hOAQjr","quality":"480p","size":"150MB","host":"FastDL","isDirect":true,"via":"hdhub.boats"},{"label":"480P Direct","url":"https://filebee.xyz/file/6a3db60086d6cba55467e7bc","quality":"480p","size":"150MB","host":"FileBee","isDirect":true,"via":"hdhub.boats"},{"label":"480P Direct","url":"https://fastdl.zip/embed.php?download=5Q1QKSIerNg4Y83tHNX25l3mX","quality":"480p","size":"150MB","host":"FastDL","isDirect":true,"via":"hdhub.boats"},{"label":"480P Direct","url":"https://filebee.xyz/file/6a3db63c86d6cba55467ead5","quality":"480p","size":"150MB","host":"FileBee","isDirect":true,"via":"hdhub.boats"},{"label":"480P Direct","url":"https://fastdl.zip/embed.php?download=NSiGSdOyqwnHra0BxkBD9hEL3","quality":"480p","size":"150MB","host":"FastDL","isDirect":true,"via":"hdhub.boats"},{"label":"480P Direct","url":"https://filebee.xyz/file/6a3db65186d6cba55467ebee","quality":"480p","size":"150MB","host":"FileBee","isDirect":true,"via":"hdhub.boats"},{"label":"480P Direct","url":"https://vcloud.zip/ja91asxwjywwfwa","quality":"480p","size":"150MB","host":"VCloud","isDirect":true,"via":"hdhub.boats"},{"label":"480P Direct","url":"https://vcloud.zip/6exa6vaeoqge1cb","quality":"480p","size":"150MB","host":"VCloud","isDirect":true,"via":"hdhub.boats"},{"label":"480P Direct","url":"https://vcloud.zip/31dzteklordd41m","quality":"480p","size":"150MB","host":"VCloud","isDirect":true,"via":"hdhub.boats"},{"label":"480P Direct","url":"https://vcloud.zip/n0pl-3nr_003sul","quality":"480p","size":"150MB","host":"VCloud","isDirect":true,"via":"hdhub.boats"},{"label":"480P Direct","url":"https://vcloud.zip/lcumrzudmazddid","quality":"480p","size":"150MB","host":"VCloud","isDirect":true,"via":"hdhub.boats"},{"label":"480P Direct","url":"https://vcloud.zip/fz-uj1olnuk-f15","quality":"480p","size":"150MB","host":"VCloud","isDirect":true,"via":"hdhub.boats"},{"label":"480P Direct","url":"https://vcloud.zip/8uxihvcw5k25-tc","quality":"480p","size":"150MB","host":"VCloud","isDirect":true,"via":"hdhub.boats"},{"label":"480P Direct","url":"https://vcloud.zip/1txv3xtgqxitgq3","quality":"480p","size":"150MB","host":"VCloud","isDirect":true,"via":"hdhub.boats"},{"label":"Direct Download","url":"https://fastdl.zip/embed.php?download=svcjHIku1ZamtIUOKl0MqttML","quality":"","size":"","host":"FastDL","isDirect":true,"via":"hdhub.boats"},{"label":"Direct Download","url":"https://vcloud.zip/aerrmcrrkiq5qqr","quality":"","size":"","host":"VCloud","isDirect":true,"via":"hdhub.boats"},{"label":"Direct Download","url":"https://filebee.xyz/file/6a3db68086d6cba55467eecc","quality":"","size":"","host":"FileBee","isDirect":true,"via":"hdhub.boats"},{"label":"720P Direct","url":"https://fastdl.zip/embed.php?download=DqyovFsadbCFel1Tyw1PROkab","quality":"720p","size":"1.2GB","host":"FastDL","isDirect":true,"via":"hdhub.boats"},{"label":"720P Direct","url":"https://filebee.xyz/file/6a3daf1086d6cba554678c5a","quality":"720p","size":"1.2GB","host":"FileBee","isDirect":true,"via":"hdhub.boats"},{"label":"720P Direct","url":"https://fastdl.zip/embed.php?download=KSK4l1IdP8Ndw7FXRNZzxvTzM","quality":"720p","size":"1.2GB","host":"FastDL","isDirect":true,"via":"hdhub.boats"},{"label":"720P Direct","url":"https://filebee.xyz/file/6a3daf2586d6cba554678d66","quality":"720p","size":"1.2GB","host":"FileBee","isDirect":true,"via":"hdhub.boats"},{"label":"720P Direct","url":"https://fastdl.zip/embed.php?download=vqhlssjVmeqk3pXXi8z62LXrX","quality":"720p","size":"1.2GB","host":"FastDL","isDirect":true,"via":"hdhub.boats"},{"label":"720P Direct","url":"https://filebee.xyz/file/6a3daf3f86d6cba554678f3d","quality":"720p","size":"1.2GB","host":"FileBee","isDirect":true,"via":"hdhub.boats"},{"label":"720P Direct","url":"https://fastdl.zip/embed.php?download=IyeXrd7whwNvvmcoq2SpWHQka","quality":"720p","size":"1.2GB","host":"FastDL","isDirect":true,"via":"hdhub.boats"},{"label":"720P Direct","url":"https://filebee.xyz/file/6a3daf5686d6cba5546790ac","quality":"720p","size":"1.2GB","host":"FileBee","isDirect":true,"via":"hdhub.boats"},{"label":"720P Direct","url":"https://fastdl.zip/embed.php?download=AuYsr1qcMbooM3SAWucykkXOp","quality":"720p","size":"1.2GB","host":"FastDL","isDirect":true,"via":"hdhub.boats"},{"label":"720P Direct","url":"https://filebee.xyz/file/6a3daf7c86d6cba554679381","quality":"720p","size":"1.2GB","host":"FileBee","isDirect":true,"via":"hdhub.boats"},{"label":"720P Direct","url":"https://fastdl.zip/embed.php?download=nLTHuDUgIOTBt25tyCIDGkidh","quality":"720p","size":"1.2GB","host":"FastDL","isDirect":true,"via":"hdhub.boats"},{"label":"720P Direct","url":"https://filebee.xyz/file/6a3daf8f86d6cba55467949b","quality":"720p","size":"1.2GB","host":"FileBee","isDirect":true,"via":"hdhub.boats"},{"label":"720P Direct","url":"https://fastdl.zip/embed.php?download=4M0EnvdQfdpzFFtxBZCYzzI58","quality":"720p","size":"1.2GB","host":"FastDL","isDirect":true,"via":"hdhub.boats"},{"label":"720P Direct","url":"https://filebee.xyz/file/6a3dafac86d6cba554679648","quality":"720p","size":"1.2GB","host":"FileBee","isDirect":true,"via":"hdhub.boats"},{"label":"720P Direct","url":"https://fastdl.zip/embed.php?download=oQmqR47w81nfELrQ5wQQMPc5s","quality":"720p","size":"1.2GB","host":"FastDL","isDirect":true,"via":"hdhub.boats"},{"label":"720P Direct","url":"https://filebee.xyz/file/6a3dafce86d6cba5546797c7","quality":"720p","size":"1.2GB","host":"FileBee","isDirect":true,"via":"hdhub.boats"},{"label":"720P Direct","url":"https://vcloud.zip/o1gmqgmmlxg2vwf","quality":"720p","size":"1.2GB","host":"VCloud","isDirect":true,"via":"hdhub.boats"},{"label":"720P Direct","url":"https://vcloud.zip/r7r3ns55swarh5e","quality":"720p","size":"1.2GB","host":"VCloud","isDirect":true,"via":"hdhub.boats"},{"label":"720P Direct","url":"https://vcloud.zip/ep_1_p5gzc_etpc","quality":"720p","size":"1.2GB","host":"VCloud","isDirect":true,"via":"hdhub.boats"},{"label":"720P Direct","url":"https://vcloud.zip/99wb166hhjrrttb","quality":"720p","size":"1.2GB","host":"VCloud","isDirect":true,"via":"hdhub.boats"},{"label":"720P Direct","url":"https://vcloud.zip/qn15qevqh7bqbvi","quality":"720p","size":"1.2GB","host":"VCloud","isDirect":true,"via":"hdhub.boats"},{"label":"720P Direct","url":"https://vcloud.zip/kg4gpngdebkch11","quality":"720p","size":"1.2GB","host":"VCloud","isDirect":true,"via":"hdhub.boats"},{"label":"720P Direct","url":"https://vcloud.zip/z7gzg06yzzaig70","quality":"720p","size":"1.2GB","host":"VCloud","isDirect":true,"via":"hdhub.boats"},{"label":"720P Direct","url":"https://vcloud.zip/uoki1utnugtibe1","quality":"720p","size":"1.2GB","host":"VCloud","isDirect":true,"via":"hdhub.boats"},{"label":"Direct Download","url":"https://fastdl.zip/embed.php?download=JxKtG18P6dpWYvmZWuk9j5lRW","quality":"","size":"","host":"FastDL","isDirect":true,"via":"hdhub.boats"},{"label":"Direct Download","url":"https://vcloud.zip/cvrc1roo4jr7hnr","quality":"","size":"","host":"VCloud","isDirect":true,"via":"hdhub.boats"},{"label":"Direct Download","url":"https://filebee.xyz/file/6a3db00a86d6cba554679bba","quality":"","size":"","host":"FileBee","isDirect":true,"via":"hdhub.boats"},{"label":"1080P Direct","url":"https://fastdl.zip/embed.php?download=CvhCvQxSOvPHsxsGUbqqVOUY8","quality":"1080p","size":"3.1GB","host":"FastDL","isDirect":true,"via":"hdhub.boats"},{"label":"1080P Direct","url":"https://filebee.xyz/file/6a3da21e86d6cba55466cb5d","quality":"1080p","size":"3.1GB","host":"FileBee","isDirect":true,"via":"hdhub.boats"},{"label":"1080P Direct","url":"https://fastdl.zip/embed.php?download=1oSQQvQsxCk2ZzLV3REYPKgqR","quality":"1080p","size":"3.1GB","host":"FastDL","isDirect":true,"via":"hdhub.boats"},{"label":"1080P Direct","url":"https://filebee.xyz/file/6a3da24686d6cba55466cd21","quality":"1080p","size":"3.1GB","host":"FileBee","isDirect":true,"via":"hdhub.boats"},{"label":"1080P Direct","url":"https://fastdl.zip/embed.php?download=EjEvHRIm3kH1FxupN5PCeV9Bo","quality":"1080p","size":"3.1GB","host":"FastDL","isDirect":true,"via":"hdhub.boats"},{"label":"1080P Direct","url":"https://filebee.xyz/file/6a3da25a86d6cba55466ce85","quality":"1080p","size":"3.1GB","host":"FileBee","isDirect":true,"via":"hdhub.boats"},{"label":"1080P Direct","url":"https://fastdl.zip/embed.php?download=99rSQgd5G5rrTlORcda76VQk6","quality":"1080p","size":"3.1GB","host":"FastDL","isDirect":true,"via":"hdhub.boats"},{"label":"1080P Direct","url":"https://filebee.xyz/file/6a3da26d86d6cba55466cffc","quality":"1080p","size":"3.1GB","host":"FileBee","isDirect":true,"via":"hdhub.boats"},{"label":"1080P Direct","url":"https://fastdl.zip/embed.php?download=ABN8LnEwGUDh3KdCNJCisgUBw","quality":"1080p","size":"3.1GB","host":"FastDL","isDirect":true,"via":"hdhub.boats"},{"label":"1080P Direct","url":"https://filebee.xyz/file/6a3da28886d6cba55466d1c2","quality":"1080p","size":"3.1GB","host":"FileBee","isDirect":true,"via":"hdhub.boats"},{"label":"1080P Direct","url":"https://fastdl.zip/embed.php?download=yPyl1KZYaA07RIE9H7O5GB6Mr","quality":"1080p","size":"3.1GB","host":"FastDL","isDirect":true,"via":"hdhub.boats"},{"label":"1080P Direct","url":"https://filebee.xyz/file/6a3da2a786d6cba55466d3f4","quality":"1080p","size":"3.1GB","host":"FileBee","isDirect":true,"via":"hdhub.boats"},{"label":"1080P Direct","url":"https://fastdl.zip/embed.php?download=7On32SKx9FzJW7rB2eMOjKctT","quality":"1080p","size":"3.1GB","host":"FastDL","isDirect":true,"via":"hdhub.boats"},{"label":"1080P Direct","url":"https://filebee.xyz/file/6a3da2b786d6cba55466d490","quality":"1080p","size":"3.1GB","host":"FileBee","isDirect":true,"via":"hdhub.boats"},{"label":"1080P Direct","url":"https://fastdl.zip/embed.php?download=aMKoNjlhHTthhIxAjxewwPVMp","quality":"1080p","size":"3.1GB","host":"FastDL","isDirect":true,"via":"hdhub.boats"},{"label":"1080P Direct","url":"https://filebee.xyz/file/6a3da2d586d6cba55466d662","quality":"1080p","size":"3.1GB","host":"FileBee","isDirect":true,"via":"hdhub.boats"},{"label":"1080P Direct","url":"https://vcloud.zip/p4yp4pol417wizn","quality":"1080p","size":"3.1GB","host":"VCloud","isDirect":true,"via":"hdhub.boats"},{"label":"1080P Direct","url":"https://vcloud.zip/kgxaagaaauuur0k","quality":"1080p","size":"3.1GB","host":"VCloud","isDirect":true,"via":"hdhub.boats"},{"label":"1080P Direct","url":"https://vcloud.zip/m6ici1mg-ybwysq","quality":"1080p","size":"3.1GB","host":"VCloud","isDirect":true,"via":"hdhub.boats"},{"label":"1080P Direct","url":"https://vcloud.zip/y91tjbll0bleayq","quality":"1080p","size":"3.1GB","host":"VCloud","isDirect":true,"via":"hdhub.boats"},{"label":"1080P Direct","url":"https://vcloud.zip/rptylbtmlhklhvn","quality":"1080p","size":"3.1GB","host":"VCloud","isDirect":true,"via":"hdhub.boats"},{"label":"1080P Direct","url":"https://vcloud.zip/npj1pp2lp25j1tl","quality":"1080p","size":"3.1GB","host":"VCloud","isDirect":true,"via":"hdhub.boats"},{"label":"1080P Direct","url":"https://vcloud.zip/gwoiyi5yonyw1od","quality":"1080p","size":"3.1GB","host":"VCloud","isDirect":true,"via":"hdhub.boats"},{"label":"1080P Direct","url":"https://vcloud.zip/ywxtwiyfbyh81tx","quality":"1080p","size":"3.1GB","host":"VCloud","isDirect":true,"via":"hdhub.boats"}],"streams":[],"ts":1784814265215}