{"ok":true,"slug":"off-campus-2026-season-1-hindi-org-multi-audio-complete-amazon-prime-web-series-480p-720p-1080p","url":"https://hdhub4us.ai.in/off-campus-2026-season-1-hindi-org-multi-audio-complete-amazon-prime-web-series-480p-720p-1080p/","title":"Off Campus (2026) Season 1 [Hindi ORG. + Multi Audio] Complete Amazon Prime WEB Series 480p | 720p | 1080p - Hdhub4u","poster":"https://hdhub4us.ai.in/wp-content/uploads/2026/05/tcPc5ZMBO4y2BtCJMe3o2nwZb2B.jpg","year":"2026","storyline":"Download Off Campus (2026) Season 1 Multi Audio [Hindi ORG. + English + Tamil + Telugu + Malayalam + Kannada] WEB Series Complete All Episodes Available in 480p 720p 1080p qualities. This Amazon Prime WEB Series is based on Drama, Romance, Sport. This Series is Available in Hindi.","genres":[],"qualities":[],"language":"Hindi Dubbed","downloads":[],"streams":[],"ts":1784754423160}