{"ok":true,"slug":"pilot-2024-amzn-web-dl-dual-audio-hindi-korean-480p-720p-1080p","url":"https://hdhub4us.ai.in/pilot-2024-amzn-web-dl-dual-audio-hindi-korean-480p-720p-1080p/","title":"Pilot (2024) AMZN WEB-DL Dual Audio {Hindi-Korean} 480p | 720p | 1080p - Hdhub4u","poster":"https://hdhub4us.ai.in/wp-content/uploads/2026/06/Pilot-2024-Hindi.webp","year":"2024","storyline":"Download Pilot (2024) WEB-DL Full Movie (Hindi-Korean) 480p 720p 1080p Qualities. This is a Korean movie and Available in 480p in [500MB] , 720p in [1.1GB] 1080p in [2.5GB] in MKV Format. This is one of the best movie based on Comedy . This Movie Is Now Available In Hindi Dubbed . This is AMZN WEB-DL Print with ORG DD 2.0 Hindi + Korean Audio and English Subtitles .","genres":[],"qualities":[],"language":"Hindi Dubbed","downloads":[],"streams":[],"ts":1784788125177}