{"ok":true,"slug":"play-and-discover-with-jose-totoy-2000-web-dl-dual-audio-hindi-english","url":"https://hdhub4us.ai.in/play-and-discover-with-jose-totoy-2000-web-dl-dual-audio-hindi-english/","title":"Play And Discover With Jose Totoy (2000) WEB-DL Dual Audio {Hindi-English} - Hdhub4u","poster":"https://hdhub4us.ai.in/wp-content/uploads/2026/06/Play.webp","year":"2000","storyline":"Play And Discover With Jose Totoy (2000) WEB-DL Full Movie (Hindi-English) 480p 720p 1080p Qualities. This is a English movie and Available in 480p in [150MB] , 720p in [400MB] 1080p in [920MB] in MKV Format. This is one of the best movie based on Comedy . This Movie Is Now Available In Hindi Dubbed . This is WEB-DL Print with ORG Hindi + English Audio and English Subtitles .","genres":[],"qualities":[],"language":"Hindi Dubbed","downloads":[],"streams":[],"ts":1784754178204}