{"ok":true,"slug":"the-christmas-chronicles-2-2020-dual-audio-hindi-english","url":"https://hdhub4us.ai.in/the-christmas-chronicles-2-2020-dual-audio-hindi-english/","title":"The Christmas Chronicles 2 (2020) Dual Audio {Hindi-English} - Hdhub4u","poster":"https://hdhub4us.ai.in/wp-content/uploads/2026/06/1000297350.webp","year":"2020","storyline":"Download The Christmas Chronicles 2 (2020) BluRay Full Movie (Hindi-English) 480p 720p 1080p Qualities. This is a Hollywood movie and Available in 480p in [400MB] , 720p in [1.2GB] 1080p in [2.5GB] in MKV Format. This is one of the best movie based on Adventure, Comedy, Family . This Movie Is Now Available In Hindi Dubbed [ORG] .","genres":[],"qualities":[],"language":"Hindi Dubbed","downloads":[],"streams":[],"ts":1784859143795}