{"ok":true,"slug":"the-librarians-season-1-4-hindi-dubbed-org-complete-series-web-dl-480p-720p-1080p","url":"https://hdhub4us.ai.in/the-librarians-season-1-4-hindi-dubbed-org-complete-series-web-dl-480p-720p-1080p/","title":"The Librarians (Season 1 – 4) Hindi Dubbed ORG. Complete Series WEB-DL 480p | 720p | 1080p - Hdhub4u","poster":"https://hdhub4us.ai.in/wp-content/uploads/2026/06/jnEzRcKFqaSXLAP87gVKTXawwGg-1.webp","year":"","storyline":"Download The Librarians Season 1 – 4 (2013-2018) Hindi Dubbed ORG TV Series Complete All Episodes Available in 480p 720p qualities. This Hindi Dubbed WEB Series is based on Action, Adventure, Comedy, Drama, Fantasy . This Series is Available in Hindi .","genres":[],"qualities":[],"language":"Hindi Dubbed","downloads":[],"streams":[],"ts":1784802096575}