{"ok":true,"slug":"zombeid-2026-urdu-hdtc-full-movie-480p-720p-1080p","url":"https://hdhub4us.ai.in/zombeid-2026-urdu-hdtc-full-movie-480p-720p-1080p/","title":"Zombeid (2026) Urdu HDTC Full Movie 480p | 720p | 1080p - Hdhub4u","poster":"https://hdhub4us.ai.in/wp-content/uploads/2026/06/Zombeid-2026.webp","year":"2026","storyline":"Download Zombeid (2026) Urdu Full Movie and available in 480p 720p 1080p . This movie is based on Romance, Thriller, Action and available in Urdu.","genres":[],"qualities":[],"language":"Hindi Dubbed","downloads":[{"label":"720P Direct","url":"https://hubcloud.cx/drive/l3lat1cqiuzgvdy","quality":"720p","size":"346.7 MB","host":"HubCloud","isDirect":true,"via":"hdhub.boats"},{"label":"720P Direct","url":"https://new5.filepress.wiki/file/6a21a144e1fed4f35151e377","quality":"720p","size":"346.7 MB","host":"FilePress","isDirect":true,"via":"hdhub.boats"},{"label":"480P Direct","url":"https://hubcloud.cx/drive/g1m3ybqdsc3qqbw","quality":"480p","size":"346.7 MB","host":"HubCloud","isDirect":true,"via":"hdhub.boats"},{"label":"480P Direct","url":"https://new5.filepress.wiki/file/6a21a144e1fed4f35151e394","quality":"480p","size":"346.7 MB","host":"FilePress","isDirect":true,"via":"hdhub.boats"},{"label":"720P Direct","url":"https://hubcloud.cx/drive/ibs21jjgbh0k1g3","quality":"720p","size":"816.15 MB","host":"HubCloud","isDirect":true,"via":"hdhub.boats"},{"label":"720P Direct","url":"https://new5.filepress.wiki/file/6a21a145e1fed4f35151e3e0","quality":"720p","size":"816.15 MB","host":"FilePress","isDirect":true,"via":"hdhub.boats"}],"streams":[],"ts":1784814407217}