{"ok":true,"slug":"lukkhe-2026-s01-hindi-amazon","title":"Lukkhe (2026) S01 Hindi Amazon WEB-DL – 480P | 720P | 1080P – x264 – 1.6GB | 2.3GB | 4.5GB – Download & Watch Online","poster":"https://m.media-amazon.com/images/S/pv-target-images/5c04cfa01f41b8da7131db12ea98a4d85f3c96c7ba081b7130db776ad870114c.jpg","uploadDate":"3 months ago","author":"SK Movies","categories":["1080p","TV Series","Web Series","10Bits","3D","4K UHD","60FPS Movies","Addatimes Originals","African Movies","Animation Movies","Anime","Arabic Movies","Asian Adult Movies","Assamese","Australian Movies","Bangla Dubbed","Bengali Movies","Bindastimes","Binge Originals","Bioscope Originals","Bollywood Movies","Canada Movies","Cantonese","Cartoon Series","Charlie Chaplin Movies","China Movies","Chinese Movies","Chorki Originals","Danish Movies","Documentary","Dual/Multi Audio Movies","Dutch Movies","Filipino Movies","Finland Movie","Fliz Movies","Foreign Language Film","France Movies","French Movies","German Movies","Germany Movies","Greece Movies","Gujarati Movie","Gupchup","HEVC","Hindi Dubbed Movies","Hoichoi Originals","Hollywood Movies","Hong Kong","Horror Movies","Hotshots Originals","Imdb Top 250 Hindi Movies","IMDb Top 250 Movies","Indonesia","Iranian Movies","Italian Movies","Japanese Movie","Kannada","Kannada Movies","KLiKK Original","Korean Movies/Drama","Lolypop","Malayalam Movies","Malaylam Movies","Malaysia","Mandarian","Mandarin Movies","Marathi Movies","Music Videos","MX Player","Natok & Teleflim","Nepali Movies","News","Norwegian","Others","Pakistani Movies","Panjabi Movies","Persian Movies","Philippines","Podcast","Polish Movies","Portuguese","Primeshots","Romanian Movies","Russian Movies","Sapnish Movies","Short Films","South African Movies","South Indian Movies","Spanish Movies","Sports","Swedish","Taiwan","Tamil Movies","Telugu Movies","Thai Movies","Torrent","Turkish Movies","TV SHOWS","ULLU Originals","UnRated","Unreleased Tracks","Urdo Movies","Vietnamese Movies","Watch Online"],"info":{"year":"2026","runtime":"N/A min","genre":["Action"],"releaseDate":"","country":"","language":"(Hindi)","quality":"Amazon WEB-DL","resolution":["480P, 720P, 1080P"],"size":["1.6GB, 2.3GB, 4.5GB"],"imdbRating":"N/A (N/A Votes)","rotten":"","director":"Debojit Das Purkayastha, Agrim Joshi","cast":["Raashi Khanna","Gitikka Ganju","Palak Tiwari"]},"storyline":"Lukkhe is an adrenaline filled, musical drama set in the beating heart of Punjab. Lucky, a sportsman, and Sanober, a musician, find their romance caught in the crossfires between police officer Gurbani and upcoming rapper, MC Badnaam, steering a collision course of tough choices that will come to decide the future of all things that Lucky and Badnaam hold dear.","screenshots":["https://i.ibb.co/bghLqfKC/MLSBD-Co-Lukkhe-2026-S01-Hindi-Amazon-WEB-DL-H264-AAC-1080p-Snapshot.jpg"],"trailer":"https://vimeo.com/928804663","sections":[{"section_title":"Download","downloads":[{"quality":"480P","savelinks_url":"https://joya9links.com/view/Wmyj7uB2","info":"Download Now","label":"Download in 480p quality"},{"quality":"720P","savelinks_url":"https://joya9links.com/view/fCDGsddM","info":"Download Now","label":"Download in 720p quality"},{"quality":"1080P","savelinks_url":"https://joya9links.com/view/PD4orISV","info":"Download Now","label":"Download in 1080p quality"}]}],"isMultiEpisode":false,"episodeSections":[],"downloads":[{"quality":"480P","savelinks_url":"https://joya9links.com/view/Wmyj7uB2","info":"Download Now","label":"Download in 480p quality"},{"quality":"720P","savelinks_url":"https://joya9links.com/view/fCDGsddM","info":"Download Now","label":"Download in 720p quality"},{"quality":"1080P","savelinks_url":"https://joya9links.com/view/PD4orISV","info":"Download Now","label":"Download in 1080p quality"}],"watchOnline":"","movieUrl":"https://mlsbd.co/lukkhe-2026-s01-hindi-amazon/"}