{"ok":true,"movie":{"id":"wonderful-nightmare-2026","slug":"wonderful-nightmare-2026","title":"Wonderful Nightmare (2026) Dual Audio [Hindi ORG & ENG] WEB-DL 480p, 720p & 1080p | GDRive","poster":"https://fojik.site/wp-content/uploads/5plgPtzwuIHUKMN044igzRkbd90.jpg","screenshots":[],"synopsis":"It follows a high-flying, career-driven lawyer who dies prematurely due to a clerical error in heaven.","genres":["2K 1080p Full HD","Comedy","Drama","Dual Audio","Foreign OR Others","HEVC Collection","Hindi Dubbed","Hollywood English","Romance"],"imdbRating":"","releaseDate":"2026-07-08T14:00:00+06:00","downloads":[],"streams":[],"source":"fojik","url":"https://fojik.site/movie/wonderful-nightmare-2026/"},"ts":1784797350240}