{"ok":true,"slug":"ladder-49-2004-hindi-bluray-full-movie","url":"https://new3.hdhub4u.cl/ladder-49-2004-hindi-bluray-full-movie/","title":"ladder-49-2004-hindi-bluray-full-movie","poster":"https://i3.wp.com/image.tmdb.org/t/p/w500/aJWQNUUHVcI7kvlVdUzPS9J8XHt.jpg?ssl=1","year":"","storyline":"Go to HomePage 🏠","genres":[],"qualities":[],"language":"Hindi Dubbed","downloads":[{"label":"480p⚡[440MB]","url":"https://hubcdn.sbs/file/DUPTweZw7raRIZEZFDqeGIPuM","quality":"480p","size":"440MB","host":"HubCDN","isDirect":true},{"label":"720p 10Bit HEVC [870MB]","url":"https://hubdrive.tips/file/2143042383","quality":"480p","size":"440MB","host":"HubDrive","isDirect":true},{"label":"720p x264 [1.1GB]","url":"https://gadgetsweb.xyz/?id=VjM4VVZWb2FDRm4zd2RkWm52M1lMS08wWWdaeUt0YW1QZWt1dU9uRFFPbFhVM2FFaVJKRHhwV1VZaGtwMUFoWm83bWFCYXF4L0pnVkFDOXNib3BPUDUxTFRrZVJsWFRjOFc2WU8wWCtpeFk9","quality":"720p","size":"870MB","host":"GadgetsWeb","isDirect":true},{"label":"1080p 10Bit HEVC [1.9GB]","url":"https://hubdrive.tips/file/3026096570","quality":"720p","size":"1.1GB","host":"HubDrive","isDirect":true},{"label":"1080p x264 [2.5GB]","url":"https://gadgetsweb.xyz/?id=VjM4VVZWb2FDRm4zd2RkWm52M1lMS08wWWdaeUt0YW1QZWt1dU9uRFFPbFhVM2FFaVJKRHhwV1VZaGtwMUFoWnZmK1ptdllsZmJwVVpqZkkrL0xxR1FrcHFhOUphdGlrS0d6c2MzUitUSkE9","quality":"1080p","size":"1.9GB","host":"GadgetsWeb","isDirect":true},{"label":"HQ 1080p BluRay [8.8GB]","url":"https://hubdrive.tips/file/3287490782","quality":"1080p","size":"2.5GB","host":"HubDrive","isDirect":true},{"label":"WATCH","url":"https://hdstream4u.com/file/z1xzpkivxysz","quality":"1080p","size":"8.8GB","host":"HDStream4U","isDirect":true},{"label":"PLAYER-2","url":"https://hubstream.art/#ucv8td","quality":"","size":"","host":"HubStream","isDirect":true}],"streams":[{"label":"Watch Player 1 (HDStream / Direct HLS)","url":"https://hdstream4u.com/file/z1xzpkivxysz","host":"HDStream"},{"label":"Watch Player 2 (HubStream)","url":"https://hubstream.art/#ucv8td","host":"HubStream"}],"ts":1784814721917}