{"ok":true,"slug":"rabb-da-radio-3-2026-webrip-punjabi-full-movie","url":"https://new3.hdhub4u.cl/rabb-da-radio-3-2026-webrip-punjabi-full-movie/","title":"rabb-da-radio-3-2026-webrip-punjabi-full-movie","poster":"https://i3.wp.com/image.tmdb.org/t/p/w400/uXgnaogJMjzNs2pnZkcGM1EulOa.jpg?ssl=1","year":"","storyline":"Go to HomePage 🏠","genres":[],"qualities":[],"language":"Hindi Dubbed","downloads":[{"label":"480p⚡[420MB]","url":"https://hubdrive.tips/file/1872940241","quality":"480p","size":"420MB","host":"HubDrive","isDirect":true},{"label":"720p HEVC [700MB]","url":"https://hubdrive.tips/file/2325213401","quality":"480p","size":"420MB","host":"HubDrive","isDirect":true},{"label":"720p x264 [1GB]","url":"https://gadgetsweb.xyz/?id=S2ZLTmtSK09zV3NodFNRYi9pblF4VHBMNVNnMjdOSGdYc01KU3VrQVBMcHhJUlRqQ3BmeWxRWU5icEtrd05CcEJISGpsM1lYNDJXY1dsTlNac1V1R1VTRURlQldDaWRIak5icGcyWFhrYWc9","quality":"720p","size":"700MB","host":"GadgetsWeb","isDirect":true},{"label":"1080p HEVC [1.5GB]","url":"https://hubdrive.tips/file/2421547928","quality":"720p","size":"1GB","host":"HubDrive","isDirect":true},{"label":"1080p x264 [2.3GB]","url":"https://gadgetsweb.xyz/?id=S2ZLTmtSK09zV3NodFNRYi9pblF4VHBMNVNnMjdOSGdYc01KU3VrQVBMcHhJUlRqQ3BmeWxRWU5icEtrd05CcGphOEFJVFRIaEJ5anZpZDdzeWUvdmFPb2FPa2FDanN6V1hRZXJUVkFGVUU9","quality":"1080p","size":"1.5GB","host":"GadgetsWeb","isDirect":true},{"label":"1080p WEB-DL [6.6GB]","url":"https://hubdrive.tips/file/8748754454","quality":"1080p","size":"2.3GB","host":"HubDrive","isDirect":true},{"label":"4K [2160p SDR WEB-DL – 12.9GB]","url":"https://hubdrive.tips/file/12831448277","quality":"1080p","size":"2.3GB","host":"HubDrive","isDirect":true},{"label":"WATCH","url":"https://hdstream4u.com/file/vjocgo0svkmc","quality":"4K","size":"12.9GB","host":"HDStream4U","isDirect":true},{"label":"PLAYER-2","url":"https://hubstream.art/#nvcgct","quality":"","size":"2.9GB","host":"HubStream","isDirect":true}],"streams":[{"label":"Watch Player 1 (HDStream / Direct HLS)","url":"https://hdstream4u.com/file/vjocgo0svkmc","host":"HDStream"},{"label":"Watch Player 2 (HubStream)","url":"https://hubstream.art/#nvcgct","host":"HubStream"}],"ts":1784773076851}