{"ok":true,"slug":"perfect-family","title":"Perfect Family Season 1 WEB-DL 1080p 720p HEVC Hindi-Korean AAC 5.1/2.0","poster":"https://image.tmdb.org/t/p/w185/4HZCp7StTidUMJvty4fZ2VJaQgm.jpg","originalTitle":"Perfect Family","synopsis":"","genres":["Bollywood Movies & Web Series Download And Watch","Drama","Family"],"cast":["Palak Bhambri"],"director":"","downloads":[{"id":"140776","url":"https://freedrivemovie.cyou/links/nqkboq6ao3/","savelinks_url":"https://freedrivemovie.cyou/links/nqkboq6ao3/","quality":"HD 1080p","language":"Hindi","size":"6GB Pack","host":"dl.freedrivemovie.org","episode":"S01 Complete","season":"Season 1"},{"id":"140775","url":"https://freedrivemovie.cyou/links/w12nbubhub/","savelinks_url":"https://freedrivemovie.cyou/links/w12nbubhub/","quality":"HD 720p","language":"Hindi","size":"850MB","host":"dl.freedrivemovie.org","episode":"S01 Complete","season":"Season 1"},{"id":"140774","url":"https://freedrivemovie.cyou/links/oacxcvjdum/","savelinks_url":"https://freedrivemovie.cyou/links/oacxcvjdum/","quality":"HD 1080p","language":"Hindi","size":"900MB Ep.","host":"dl.freedrivemovie.org","episode":"S01 Complete","season":"Season 1"}],"trailer":"https://www.youtube.com/watch?v=poyjubkbB3Q","screenshots":["https://image.tmdb.org/t/p/w500/tsDmPboTBEDiG7Bklg0OV2b3KlW.jpg","https://image.tmdb.org/t/p/w500/tsDmPboTBEDiG7Bklg0OV2b3KlW.jpg&description=Perfect"],"imdbRating":"9","source":"freedrivemovie","type":"TV","sourceUrl":"https://freedrivemovie.cyou/tvshows/perfect-family/","sections":[{"section_title":"Season 1","downloads":[{"id":"140776","url":"https://freedrivemovie.cyou/links/nqkboq6ao3/","savelinks_url":"https://freedrivemovie.cyou/links/nqkboq6ao3/","quality":"HD 1080p","language":"Hindi","size":"6GB Pack","host":"dl.freedrivemovie.org","episode":"S01 Complete","season":"Season 1"},{"id":"140775","url":"https://freedrivemovie.cyou/links/w12nbubhub/","savelinks_url":"https://freedrivemovie.cyou/links/w12nbubhub/","quality":"HD 720p","language":"Hindi","size":"850MB","host":"dl.freedrivemovie.org","episode":"S01 Complete","season":"Season 1"},{"id":"140774","url":"https://freedrivemovie.cyou/links/oacxcvjdum/","savelinks_url":"https://freedrivemovie.cyou/links/oacxcvjdum/","quality":"HD 1080p","language":"Hindi","size":"900MB Ep.","host":"dl.freedrivemovie.org","episode":"S01 Complete","season":"Season 1"}]}],"info":{"year":"","runtime":"N/A","genre":"Bollywood Movies & Web Series Download And Watch, Drama, Family","language":"Hindi","quality":"HD 1080p","director":"","cast":["Palak Bhambri"]}}