{"ok":true,"page":14,"filter":"all","items":[{"slug":"the-boys-2026-s05-dual-audio-hindi-org-english-amazon","title":"The Boys (2026) S05E07 Dual Audio [Hindi ORG-English] Amazon WEB-DL – 720P | 1080P – x264 – 700MB | 2.6GB – Download","poster":"https://i.ibb.co.com/BV4RF3kB/2026-04-08-152828.jpg","year":"2026","quality":"1080P","language":"Dual Audio","uploadDate":"2 months ago","sizes":["700MB","2.6GB"]},{"slug":"kede-chole-mon-aajkal-2026-s01-bengali-dubbed","title":"Kede Chole Mon Aajkal (2026) S01E01-05 Bengali Dubbed ORG iScreen WEB-DL – 480P | 720P | 1080P – x264 – 500MB | 1GB | 3.1GB – Download & Watch Online","poster":"https://i.ibb.co.com/wrY7C2k1/nx-Tb-Da1-Qc1aw-WL0qauqm.jpg","year":"2026","quality":"1080P","language":"Bengali","uploadDate":"2 months ago","sizes":["500MB","1GB","3.1GB"]},{"slug":"sulabh-complex-2026-bengali-fridaay-web-dl-720p-1080p-x264-400mb-1-2gb-download-watch-online","title":"Sulabh Complex (2026) Bengali Fridaay WEB-DL – 720P | 1080P – x264 – 400MB | 1.2GB – Download & Watch Online","poster":"https://i.ibb.co.com/Y4HfY7Mt/Sulabh-Complex-2026-Bengali-Fridaay-WEB-DL-H264-AAC-1080p-720p-Download.jpg","year":"2026","quality":"1080P","language":"Bengali","uploadDate":"2 months ago","sizes":["400MB","1.2GB"]},{"slug":"sangamarmar-2026-s01-dual-audio-bengali-org-hindi-jiohs","title":"Sangamarmar (2026) S01E46-47 Dual Audio [Bengali ORG-Hindi] JIOHS WEB-DL – 480P | 720P | 1080P | 4K – x264 & x265(HEVC) – 950MB | 2.5GB | 5.7GB | 19.4GB ESub- Download & Watch Online","poster":"https://i.ibb.co.com/hJ8qjM2g/Sangamarmar-2026-S01-Dual-Audio-Bengali-ORG-Hindi-JIOHS-WEB-DL-H264-AAC-4-K-1080p-720p-480p-ESu.webp","year":"2026","quality":"4K","language":"Bengali","uploadDate":"2 months ago","sizes":["950MB","2.5GB","5.7GB","19.4GB"]},{"slug":"krishnavataram-part-1-the-heart","title":"Krishnavataram Part 1 The Heart (2026) Hindi HDTC-Rip – 480P | 720P | 1080P – x264 – 500MB | 1.2GB | 2.8GB – Download & Watch Online","poster":"https://i.ibb.co.com/hFY6XhTb/krishnavataram-review-lord-krishna-story-told-beautifully-08170163-16x9.jpg","year":"2026","quality":"1080P","language":"Hindi","uploadDate":"2 months ago","sizes":["500MB","1.2GB","2.8GB"]},{"slug":"sudhu-tomaree-pratiksha-2018-bengali-amazon-web-dl-480p-720p-1080p-x264-500mb-1-2gb-2-9gb-6-7gb-download-watch-online","title":"Sudhu Tomaree Pratiksha (2018) Bengali Amazon WEB-DL – 480P | 720P | 1080P – x264 – 500MB | 1.2GB | 2.9GB | 6.7GB – Download & Watch Online","poster":"https://i.ibb.co.com/zHbs3tmy/hq720.jpg","year":"2018","quality":"1080P","language":"Bengali","uploadDate":"2 months ago","sizes":["500MB","1.2GB","2.9GB","6.7GB"]},{"slug":"the-misfits-2021-dual-audio-hindi-org-english-blu-ray-480p-720p-1080p-x264-350mb-900mb-2gb-download-watch-online","title":"The Misfits (2021) Dual Audio [Hindi ORG-English] Blu-Ray – 480P | 720P | 1080P – x264 – 350MB | 900MB | 2GB – Download & Watch Online","poster":"https://image.tmdb.org/t/p/original/tF8Ku1rFoTFrGdso1VSvcyHmN92.jpg","year":"2021","quality":"1080P","language":"Dual Audio","uploadDate":"2 months ago","sizes":["350MB","900MB","2GB"]},{"slug":"pratidwandi-2010-bengali-jhs-web-dl-480p-720p-1080p-x264-700mb-1-2gb-6-1gb-download-watch-online","title":"Pratidwandi (2010) Bengali JHS WEB-DL – 480P | 720P | 1080P – x264 – 700MB | 1.2GB | 6.1GB – Download & Watch Online","poster":"https://i.ibb.co.com/FMxrnxQ/2026-05-13-082624.jpg","year":"2010","quality":"1080P","language":"Bengali","uploadDate":"2 months ago","sizes":["700MB","1.2GB","6.1GB"]},{"slug":"main-actor-nahin-hoon-2026-hindi-hdtc-rip-480p-720p-1080p-x264-450mb-750mb-1-2gb-download","title":"Main Actor Nahin Hoon (2026) Hindi HDTC-Rip – 480P | 720P | 1080P – x264 – 450MB | 750MB | 1.2GB – Download","poster":"https://assets-in.bmscdn.com/discovery-catalog/events/et00494113-lewnwfqfge-landscape.jpg","year":"2026","quality":"1080P","language":"Hindi","uploadDate":"2 months ago","sizes":["450MB","750MB","1.2GB"]},{"slug":"kaalidas-2-2026-dual-audio-hindi-org-tamil-amazon","title":"Kaalidas 2 (2026) Dual Audio [Hindi ORG-Tamil] Amazon WEB-DL – 480P | 720P | 1080P – x264 – 650MB | 1.4GB | 2.9GB ESub- Download & Watch Online","poster":"https://i.ibb.co.com/GZKgY8F/Kaalidas-2-2026-Dual-Audio-Hindi-ORG-Tamil-Amazon-WEB-DL-H264-AAC-1080p-720p-480p-ESub.webp","year":"2026","quality":"1080P","language":"Dual Audio","uploadDate":"2 months ago","sizes":["650MB","1.4GB","2.9GB"]},{"slug":"wwe-monday-night-raw-2026-05-12-english-netflix","title":"WWE Monday Night Raw 2026 05 12 English Netflix WEB-DL – 480P | 720P | 1080P – x264 – 450MB | 2GB | 5GB – Download & Watch Online","poster":"https://i.ibb.co.com/Pst4rDTk/WWE-Monday-Night-Raw-2026-05-12-English-Net-Flix-WEB-DL-h264-AAC-1080p-720p-480p-Download.webp","year":"2026","quality":"1080P","language":"English","uploadDate":"2 months ago","sizes":["450MB","2GB","5GB"]},{"slug":"super-hit-2026-bengali-dubbed-hq-web-dl-480p-720p-1080p-x264-600mb-1-2gb-3-9gb-download-watch-online","title":"Super Hit (2026) Bengali Dubbed HQ WEB-DL – 480P | 720P | 1080P – x264 – 600MB | 1.2GB | 3.9GB – Download & Watch Online","poster":"https://i.ibb.co.com/vCrhCt3Q/Super-Hit-2026-Bengali-Dubbed.jpg","year":"2026","quality":"1080P","language":"Bengali","uploadDate":"2 months ago","sizes":["600MB","1.2GB","3.9GB"]},{"slug":"love-mocktail-3-2026-bengali-dubbed","title":"Love Mocktail 3 (2026) Bengali Dubbed HQ WEB-DL – 480P | 720P | 1080P – x264 – 600MB | 1.2GB | 3.8GB – Download & Watch Online","poster":"https://i.ibb.co.com/PZXg00cL/Love-Mocktail-3-2026-Bengali-Dubbed.jpg","year":"2026","quality":"1080P","language":"Bengali","uploadDate":"2 months ago","sizes":["600MB","1.2GB","3.8GB"]},{"slug":"vaazha-ii-biopic-of-a-billion-bros-2026-bengali-dubbed","title":"Vaazha II: Biopic of a Billion Bros (2026) Bengali Dubbed HQ WEB-DL – 480P | 720P | 1080P – x264 – 700MB | 1.5GB | 4.5GB – Download & Watch Online","poster":"https://i.ibb.co.com/xqTd2xMY/Vaazha-II-2027-Bengali-Dubbed-Movie.jpg","year":"2026","quality":"1080P","language":"Bengali","uploadDate":"2 months ago","sizes":["700MB","1.5GB","4.5GB"]},{"slug":"justice-for-jeni-2026-bengali-dubbed-hq-web-dl-480p-720p-1080p-x264-450mb-1gb-3gb-download-watch-online","title":"Justice for Jeni (2026) Bengali Dubbed HQ WEB-DL – 480P | 720P | 1080P – x264 – 450MB | 1GB | 3GB – Download & Watch Online","poster":"https://i.ibb.co.com/rfNWsS5k/Justice-For-Jeni-2027-Bengali-Dubbed.jpg","year":"2026","quality":"1080P","language":"Bengali","uploadDate":"2 months ago","sizes":["450MB","1GB","3GB"]},{"slug":"wwe-backlash-2026-english","title":"WWE Backlash (2026) English Netflix WEB-DL – 480P | 720P | 1080P – x264 – 650MB | 3.5GB | 11.1GB – Download & Watch Online","poster":"https://i.ibb.co.com/35zc1kqz/WWE-Backlash-2026-English-Netflix-WEB-DL-H264-AAC-1080p-720p-480p-Download.webp","year":"2026","quality":"1080P","language":"English","uploadDate":"2 months ago","sizes":["650MB","3.5GB","11.1GB"]},{"slug":"prodhanmontri-lu-zhen-legend-of-lu-zhen-2025-s01-bengali-dubbed","title":"Rajprashader Lu Zhen-Legend of Lu Zhen (2025) S01E41-45 Bengali Dubbed ORG DP WEB-DL – 480P | 720P | 1080P – x264 – 650MB | 1.4GB | 3.4GB – Download & Watch Online","poster":"https://i.ibb.co/W4vgXW9M/Rajprashader-Lu-Zhen-Legend-of-Lu-Zhen-2025-S01-E11-16-Bengali-Dubbed-ORG-DP-WEB-DL-H264-AAC-1080p-7.webp","year":"2025","quality":"1080P","language":"Bengali","uploadDate":"2 months ago","sizes":["650MB","1.4GB","3.4GB"]},{"slug":"the-kerala-story-2-2026-bengali-dubbed","title":"The Kerala Story 2: Goes Beyond (2026) Bengali Dubbed HQ WEB-DL – 480P | 720P | 1080P – x264 – 600MB | 1.2GB | 3.9GB – Download & Watch Online","poster":"https://i.ibb.co.com/yBm8ZkT8/The-Kerala-Story-2-Goes-Beyond-2026-Bengali-Dubbed-HQ.jpg","year":"2026","quality":"1080P","language":"Bengali","uploadDate":"2 months ago","sizes":["600MB","1.2GB","3.9GB"]},{"slug":"lal-salaam-2024-bengali-dubbed-hq-web-dl-480p-720p-1080p-x264-600mb-1-3gb-4-1gb-download-watch-online","title":"Lal Salaam (2024) Bengali Dubbed HQ WEB-DL – 480P | 720P | 1080P – x264 – 600MB | 1.3GB | 4.1GB – Download & Watch Online","poster":"https://i.ibb.co.com/7tnqSshk/Laal-Salaam-2027-Bengali-Dubbed-HQ-WEB-DL-H264-AAC-1080p-720p-480p-Download.jpg","year":"2024","quality":"1080P","language":"Bengali","uploadDate":"2 months ago","sizes":["600MB","1.3GB","4.1GB"]},{"slug":"dacoit-a-love-story-2026-bengali-dubbed-hq-web-dl-480p-720p-1080p-x264-650mb-1-4gb-4-3gb-download-watch-online","title":"Dacoit: A Love Story (2026) Bengali Dubbed HQ WEB-DL – 480P | 720P | 1080P – x264 – 650MB | 1.4GB | 4.3GB – Download & Watch Online","poster":"https://i.ibb.co.com/mCVrqGzQ/Dacoit-A-Love-Story-2026-Bengali-Dubbed.jpg","year":"2026","quality":"1080P","language":"Bengali","uploadDate":"2 months ago","sizes":["650MB","1.4GB","4.3GB"]},{"slug":"laalo-krishna-sada-sahaayate-2025-bengali-dubbed","title":"Laalo: Krishna Sada Sahaayate (2025) Bengali Dubbed HQ WEB-DL – 480P | 720P | 1080P – x264 – 600MB | 1.3GB | 3.9GB – Download & Watch Online","poster":"https://i.ibb.co.com/fdzjp04p/Laal-Salaam-2027-Bengali-Dubbed.jpg","year":"2025","quality":"1080P","language":"Bengali","uploadDate":"2 months ago","sizes":["600MB","1.3GB","3.9GB"]},{"slug":"ten-hours-2025-kannada-snxt-web-dl-480p-720p-1080p-x264-450mb-1-3gb-2-2gb-esub-download-watch-online","title":"Ten Hours (2025) UNCUT Dual Audio [Hindi ORG-Tamil] Amazon WEB-DL – 480P | 720P | 1080P – x264 – 350MB | 1.3GB | 3.2GB – Download & Watch Online","poster":"https://m.media-amazon.com/images/S/pv-target-images/8621ef310498280341f7ae4c3ba309b77516f481f11fc82589f726bbf6eb25b8.jpg","year":"2025","quality":"1080P","language":"Dual Audio","uploadDate":"2 months ago","sizes":["350MB","1.3GB","3.2GB"]},{"slug":"project-hail-mary-2026-dual-audio-hindi-org-english-itunes","title":"Project Hail Mary (2026) Dual Audio [Hindi ORG-English] iTunes WEB-DL – 480P | 720P | 1080P | 4K – x264 – 400MB | 1.7GB | 4.2GB | 23.8GB – Download & Watch Online","poster":"https://i.ibb.co.com/dsxTB9Vd/Project-Hail-Mary-movie-review.jpg","year":"2026","quality":"4K","language":"Dual Audio","uploadDate":"2 months ago","sizes":["400MB","1.7GB","4.2GB","23.8GB"]}],"hasMore":true}