{"ok":true,"page":63,"totalPages":75,"items":[{"id":"pets-on-a-train-2025","slug":"pets-on-a-train-2025","title":"Pets on a Train (2025) Dual Audio [Hindi ORG & ENG] WEB-DL 480p, 720p & 1080p | GDRive","poster":"https://fojik.site/wp-content/uploads/b10qy1KwrfmH0MGS2rBUJ0BxgYB.jpg","quality":"ORG","year":"2025","rating":"","source":"fojik","url":"https://fojik.site/movie/pets-on-a-train-2025/"},{"id":"the-spongebob-movie-search-for-squarepants-2025","slug":"the-spongebob-movie-search-for-squarepants-2025","title":"The SpongeBob Movie: Search for SquarePants (2025) Dual Audio [Hindi ORG & ENG] WEB-DL 480p, 720p & 1080p | GDRive","poster":"https://fojik.site/wp-content/uploads/pDWYW9v8fmJdA7N0I1MOdQA3ETq.jpg","quality":"ORG","year":"2025","rating":"","source":"fojik","url":"https://fojik.site/movie/the-spongebob-movie-search-for-squarepants-2025/"},{"id":"18-how-not-to-summon-a-demon-lord","slug":"18-how-not-to-summon-a-demon-lord","title":"18+ How NOT to Summon a Demon Lord : Season 1-2 [ ENG & Japanese] WEB-DL 720p HEVC | ESub | [Complete]","poster":"https://fojik.site/wp-content/uploads/OSgmyqKXiH7vIXu0zzPHNqZl84.jpg","quality":"WEB-DL","year":"","rating":"","source":"fojik","url":"https://fojik.site/movie/18-how-not-to-summon-a-demon-lord/"},{"id":"the-mighty-nein","slug":"the-mighty-nein","title":"The Mighty Nein : Season 1 Dual Audio [Hindi ORG & ENG] WEB-DL 720p HEVC | [Epi 1-8 All Added – Complete]","poster":"https://fojik.site/wp-content/uploads/cBklO4MCv9OLAekFfVNvbe7IDv3.jpg","quality":"ORG","year":"","rating":"","source":"fojik","url":"https://fojik.site/movie/the-mighty-nein/"},{"id":"tales-of-the-teenage-mutant-ninja-turtles","slug":"tales-of-the-teenage-mutant-ninja-turtles","title":"Tales of the Teenage Mutant Ninja Turtles : Season 1-2 WEB-DL 720p HEVC | [Complete]","poster":"https://fojik.site/wp-content/uploads/eCOoBMVFm5UgoKAZ35HdOC9cCwt.jpg","quality":"WEB-DL","year":"","rating":"","source":"fojik","url":"https://fojik.site/movie/tales-of-the-teenage-mutant-ninja-turtles/"},{"id":"rick-and-morty","slug":"rick-and-morty","title":"Rick and Morty : Season 1-8 BluRay 720p HEVC | [Complete]","poster":"https://fojik.site/wp-content/uploads/WGRQ8FpjkDTzivQJ43t94bOuY0.jpg","quality":"BLURAY","year":"","rating":"","source":"fojik","url":"https://fojik.site/movie/rick-and-morty/"},{"id":"in-your-dreams-2025-web-dl-480p-720p-1080p-gdrive","slug":"in-your-dreams-2025-web-dl-480p-720p-1080p-gdrive","title":"In Your Dreams (2025) Dual Audio [Hindi ORG & ENG] WEB-DL 480p, 720p & 1080p | GDRive","poster":"https://fojik.site/wp-content/uploads/41sUrWLy9bZ0LtZi8IcLlPc7id5.jpg","quality":"ORG","year":"2025","rating":"","source":"fojik","url":"https://fojik.site/movie/in-your-dreams-2025-web-dl-480p-720p-1080p-gdrive/"},{"id":"kurukshetra","slug":"kurukshetra","title":"Kurukshetra: The Great War of Mahabharata : Season 1 [Part 1 & 2] Hindi WEB-DL 720p HEVC | [Complete]","poster":"https://fojik.site/wp-content/uploads/amNFukSD0hpj5omLkikfaNw42sp.jpg","quality":"WEB-DL","year":"","rating":"","source":"fojik","url":"https://fojik.site/movie/kurukshetra/"},{"id":"the-twits-2025-web-dl-480p-720p-1080p-gdrive","slug":"the-twits-2025-web-dl-480p-720p-1080p-gdrive","title":"The Twits (2025) Dual Audio [Hindi ORG & ENG] WEB-DL 480p, 720p & 1080p | GDRive","poster":"https://fojik.site/wp-content/uploads/izYZGeOHhPWiga8Hb5P4JYfcH8T.jpg","quality":"ORG","year":"2025","rating":"","source":"fojik","url":"https://fojik.site/movie/the-twits-2025-web-dl-480p-720p-1080p-gdrive/"},{"id":"marvel-zombies","slug":"marvel-zombies","title":"Marvel Zombies : Season 1 ENGLISH WEB-DL 720p & 1080p HEVC | [Complete]","poster":"https://fojik.site/wp-content/uploads/6OMoD1CB1IqSHgxBPIyz8hUtAfP.jpg","quality":"WEB-DL","year":"","rating":"","source":"fojik","url":"https://fojik.site/movie/marvel-zombies/"},{"id":"mahavatar-narsimha-2025","slug":"mahavatar-narsimha-2025","title":"Mahavatar Narsimha (2025) Official Hindi WEB-DL 480p, 720p & 1080p | GDRive","poster":"https://fojik.site/wp-content/uploads/uGTF87VyfjtwwqRlT2apQg5YnEp.jpg","quality":"WEB-DL","year":"2025","rating":"","source":"fojik","url":"https://fojik.site/movie/mahavatar-narsimha-2025/"},{"id":"elio-2025","slug":"elio-2025","title":"Elio (2025) Dual Audio [Hindi ORG & ENG] WEB-DL 480p, 720p & 1080p | GDRive","poster":"https://fojik.site/wp-content/uploads/w2ARwtc1zoh0pyfwmyhpZHwuXgK.jpg","quality":"ORG","year":"2025","rating":"","source":"fojik","url":"https://fojik.site/movie/elio-2025/"},{"id":"wolf-king","slug":"wolf-king","title":"Wolf King : Season 1-2 Dual Audio [Hindi ORG & ENG] NF WEB-DL 720p HEVC | [Complete]","poster":"https://fojik.site/wp-content/uploads/tC6mrnKKASpoJwIW37BquR4cyER.jpg","quality":"ORG","year":"","rating":"","source":"fojik","url":"https://fojik.site/movie/wolf-king/"},{"id":"lilo-stitch-2025-web-dl-480p-720p-1080p-gdrive","slug":"lilo-stitch-2025-web-dl-480p-720p-1080p-gdrive","title":"Lilo & Stitch (2025) Dual Audio [Hindi ORG & ENG] WEB-DL 480p, 720p & 1080p | GDRive","poster":"https://fojik.site/wp-content/uploads/gdLU0J81mjcYEMFUqb6WiLYYr7j.jpg","quality":"ORG","year":"2025","rating":"","source":"fojik","url":"https://fojik.site/movie/lilo-stitch-2025-web-dl-480p-720p-1080p-gdrive/"},{"id":"the-bad-guys-2-2025","slug":"the-bad-guys-2-2025","title":"The Bad Guys 2 (2025) Dual Audio [Hindi ORG & ENG] WEB-DL 480p, 720p & 1080p | GDRive","poster":"https://fojik.site/wp-content/uploads/fAB4bjrQJ3k0ObTZ4SbJnLLL3yz.jpg","quality":"ORG","year":"2025","rating":"","source":"fojik","url":"https://fojik.site/movie/the-bad-guys-2-2025/"},{"id":"smurfs-2025","slug":"smurfs-2025","title":"Smurfs (2025) Dual Audio [Hindi ORG & ENG] WEB-DL 480p, 720p & 1080p | GDRive","poster":"https://fojik.site/wp-content/uploads/8o6lkhL32xQJeB52IIG1us5BVey.jpg","quality":"ORG","year":"2025","rating":"","source":"fojik","url":"https://fojik.site/movie/smurfs-2025/"},{"id":"watchmen-chapter-ii-2024","slug":"watchmen-chapter-ii-2024","title":"Watchmen: Chapter II (2024) Dual Audio [Hindi ORG & ENG] WEB-DL HEVC 720p & 1080p | GDRive","poster":"https://fojik.site/wp-content/uploads/4rBObJFpiWJOG7aIlRrOUniAkBs.jpg","quality":"ORG","year":"2024","rating":"","source":"fojik","url":"https://fojik.site/movie/watchmen-chapter-ii-2024/"},{"id":"watchmen-chapter-i-2024","slug":"watchmen-chapter-i-2024","title":"Watchmen: Chapter I (2024) Dual Audio [Hindi ORG & ENG] WEB-DL 480p, 720p & 1080p | GDRive","poster":"https://fojik.site/wp-content/uploads/tE2vZ6HdlmKaBh0wpsvHCf7HJKo.jpg","quality":"ORG","year":"2024","rating":"","source":"fojik","url":"https://fojik.site/movie/watchmen-chapter-i-2024/"},{"id":"sausage-party-foodtopia","slug":"sausage-party-foodtopia","title":"Sausage Party: Foodtopia : Season 1-2 Dual Audio [Hindi ORG & ENG] WEB-DL 720p HEVC | [Complete]","poster":"https://fojik.site/wp-content/uploads/wikdL6IcHjSJSbUv4iYTCwJn8.jpg","quality":"ORG","year":"","rating":"","source":"fojik","url":"https://fojik.site/movie/sausage-party-foodtopia/"},{"id":"mobile-suit-gundam-gquuuuuux-beginning","slug":"mobile-suit-gundam-gquuuuuux-beginning","title":"Mobile Suit Gundam GQuuuuuuX: Beginning : Season 1 Dual/Multi Audio [Hindi ORG, ENG & Japanese] BluRay 720p HEVC | [Epi 1-12 All Added – Complete Zip Batch]","poster":"https://fojik.site/wp-content/uploads/64gLFUuTUsoeQ1SOSFw7Q7w8kEF.jpg","quality":"ORG","year":"","rating":"","source":"fojik","url":"https://fojik.site/movie/mobile-suit-gundam-gquuuuuux-beginning/"}],"hasMore":true,"source":"fojik","ts":1784800008757}