{"ok":true,"page":4,"totalPages":75,"items":[{"id":"aas-2026","slug":"aas-2026","title":"Aakhri Sawal (2026) Hindi PRE-HD 480p, 720p & 1080p | GDRive","poster":"https://fojik.site/wp-content/uploads/9CXBZH6sRJpFTMSaY3wj1jx98F4.jpg","quality":"PRE-HD","year":"2026","rating":"","source":"fojik","url":"https://fojik.site/movie/aas-2026/"},{"id":"indian-institute-of-zombies-2026","slug":"indian-institute-of-zombies-2026","title":"Indian Institute of Zombies (2026) Hindi PRE-HD 480p, 720p & 1080p | GDRive","poster":"https://fojik.site/wp-content/uploads/iiz-indian-institute-of-zombies-et00496075-1777267863.jpg","quality":"PRE-HD","year":"2026","rating":"","source":"fojik","url":"https://fojik.site/movie/indian-institute-of-zombies-2026/"},{"id":"kartavya-2026","slug":"kartavya-2026","title":"Kartavya (2026) Hindi WEB-DL 480p, 720p & 1080p | GDRive","poster":"https://fojik.site/wp-content/uploads/wyJG0JzeZTo37giko4UJVVFktld.jpg","quality":"WEB-DL","year":"2026","rating":"","source":"fojik","url":"https://fojik.site/movie/kartavya-2026/"},{"id":"vimal-khanna","slug":"vimal-khanna","title":"Vimal Khanna : Season 1 Hindi WEB-DL 720p HEVC | [Complete]","poster":"https://fojik.site/wp-content/uploads/m9LPznYLoW00Egaj1JpCpvFYtYD.jpg","quality":"WEB-DL","year":"","rating":"","source":"fojik","url":"https://fojik.site/movie/vimal-khanna/"},{"id":"inspector-avinash","slug":"inspector-avinash","title":"Inspector Avinash : Season 1-2 Hindi WEB-DL 720p HEVC | [Complete]","poster":"https://fojik.site/wp-content/uploads/zxc45q5mulZkPXYi4g3a9LxV4sH.jpg","quality":"WEB-DL","year":"","rating":"","source":"fojik","url":"https://fojik.site/movie/inspector-avinash/"},{"id":"krishnavataram-part-1-the-heart-2026","slug":"krishnavataram-part-1-the-heart-2026","title":"Krishnavataram Part 1: The Heart (2026) Hindi PRE-HD 480p, 720p & 1080p | GDRive","poster":"https://fojik.com/wp-content/uploads/fAitSsAH5pMRDgaItQbHyq0jWmI.jpg","quality":"PRE-HD","year":"2026","rating":"","source":"fojik","url":"https://fojik.com/movie/krishnavataram-part-1-the-heart-2026/"},{"id":"lukkhe","slug":"lukkhe","title":"Lukkhe : Season 1 Hindi WEB-DL 720p HEVC | [Complete]","poster":"https://fojik.com/wp-content/uploads/w8GLkht5ceCi7KQ3AMD77mzkxBc.jpg","quality":"WEB-DL","year":"","rating":"","source":"fojik","url":"https://fojik.com/movie/lukkhe/"},{"id":"chhota-bheem-and-little-singham-the-rise-of-betal-2026","slug":"chhota-bheem-and-little-singham-the-rise-of-betal-2026","title":"Chhota Bheem and Little Singham: The Rise of Betal (2026) Hindi WEB-DL 480p, 720p & 1080p | GDRive","poster":"https://fojik.com/wp-content/uploads/vZ8K4kCNyAIShil9Swu3XsdmQVU.jpg","quality":"WEB-DL","year":"2026","rating":"","source":"fojik","url":"https://fojik.com/movie/chhota-bheem-and-little-singham-the-rise-of-betal-2026/"},{"id":"tapak","slug":"tapak","title":"Tapak (2025) Hindi WEB-DL 480p, 720p & 1080p | GDRive","poster":"https://fojik.com/wp-content/uploads/image-2026-05-03T162606.341.png","quality":"WEB-DL","year":"2025","rating":"","source":"fojik","url":"https://fojik.com/movie/tapak/"},{"id":"the-great-indian-kapil-show","slug":"the-great-indian-kapil-show","title":"The Great Indian Kapil Show : Season 1-4 Hindi WEB-DL 720p HEVC | [S01-3 Complete & S04 Epi 1-14 Added]","poster":"https://fojik.com/wp-content/uploads/6LWtSm2VHfenFBMvmjG9GYgfvSd.jpg","quality":"WEB-DL","year":"","rating":"","source":"fojik","url":"https://fojik.com/movie/the-great-indian-kapil-show/"},{"id":"sapne-vs-everyone","slug":"sapne-vs-everyone","title":"Sapne Vs Everyone : Season 1-2 Hindi WEB-DL 720p HEVC | [Complete]","poster":"https://fojik.com/wp-content/uploads/ajBMZ9JNpfrecj4xpZz49tCONBm.jpg","quality":"WEB-DL","year":"","rating":"","source":"fojik","url":"https://fojik.com/movie/sapne-vs-everyone/"},{"id":"glory","slug":"glory","title":"Glory : Season 1 Hindi WEB-DL 720p HEVC | [Complete]","poster":"https://fojik.com/wp-content/uploads/juAQ7fFQGu2n3A2gW5tfNub1cW8.jpg","quality":"WEB-DL","year":"","rating":"","source":"fojik","url":"https://fojik.com/movie/glory/"},{"id":"ginny-weds-sunny-2020","slug":"ginny-weds-sunny-2020","title":"Ginny Weds Sunny (2020) Hindi NF WEB-DL 480p, 720p & 1080p | GDRive","poster":"https://fojik.com/wp-content/uploads/EC3K9Zv7uzpXomJWuRMiQH9g5V.jpg","quality":"WEB-DL","year":"2020","rating":"","source":"fojik","url":"https://fojik.com/movie/ginny-weds-sunny-2020/"},{"id":"nukkad-naatak-2026","slug":"nukkad-naatak-2026","title":"Nukkad Naatak (2026) Hindi WEB-DL 480p, 720p & 1080p | GDRive","poster":"https://fojik.com/wp-content/uploads/ouT4jOENHVyQ1tvrVK78CP9CBoq.jpg","quality":"WEB-DL","year":"2026","rating":"","source":"fojik","url":"https://fojik.com/movie/nukkad-naatak-2026/"},{"id":"badass-ravikumar-2025","slug":"badass-ravikumar-2025","title":"Badass RaviKumar (2025) Hindi Official WEB-DL 480p, 720p & 1080p | GDRive","poster":"https://fojik.com/wp-content/uploads/59xcbgtx2A7uKk0HC1PhAxJARIH.jpg","quality":"WEB-DL","year":"2025","rating":"","source":"fojik","url":"https://fojik.com/movie/badass-ravikumar-2025/"},{"id":"toaster-2026","slug":"toaster-2026","title":"Toaster (2026) Hindi WEB-DL 480p, 720p & 1080p | GDRive","poster":"https://fojik.com/wp-content/uploads/bQhCscL7yV8qtod2mDpJa6S28VJ.jpg","quality":"WEB-DL","year":"2026","rating":"","source":"fojik","url":"https://fojik.com/movie/toaster-2026/"},{"id":"matka-king","slug":"matka-king","title":"Matka King : Season 1 Hindi WEB-DL 720p & 1080p HEVC | [Complete]","poster":"https://fojik.com/wp-content/uploads/rxrNudwWK4yNICIvOaKbH71cdAg.jpg","quality":"WEB-DL","year":"","rating":"","source":"fojik","url":"https://fojik.com/movie/matka-king/"},{"id":"agra-2025","slug":"agra-2025","title":"Agra (2025) Hindi WEB-DL 480p, 720p & 1080p | GDRive","poster":"https://fojik.com/wp-content/uploads/image-2026-04-17T035253.332.png","quality":"WEB-DL","year":"2025","rating":"","source":"fojik","url":"https://fojik.com/movie/agra-2025/"},{"id":"do-deewane-seher-mein-2026","slug":"do-deewane-seher-mein-2026","title":"Do Deewane Seher Mein (2026) Hindi WEB-DL 480p, 720p & 1080p | GDRive","poster":"https://fojik.com/wp-content/uploads/ucKAn0Ub5l4oZFuCdqhdJoM5lwW.jpg","quality":"WEB-DL","year":"2026","rating":"","source":"fojik","url":"https://fojik.com/movie/do-deewane-seher-mein-2026/"},{"id":"assi-2026","slug":"assi-2026","title":"Assi (2026) Hindi WEB-DL 480p, 720p & 1080p | GDRive","poster":"https://fojik.com/wp-content/uploads/image-2026-02-20T191525.836.png","quality":"WEB-DL","year":"2026","rating":"","source":"fojik","url":"https://fojik.com/movie/assi-2026/"}],"hasMore":true,"source":"fojik","ts":1784800008729}