{"ok":true,"page":103,"totalPages":186,"items":[{"id":"witchboard-2024","slug":"witchboard-2024","title":"Witchboard (2024) Dual Audio [Hindi ORG & ENG] WEB-DL 480p, 720p & 1080p | GDRive","poster":"https://fojik.com/wp-content/uploads/8RcN5FHkJVNJdOaL6WtTePU7CyF.jpg","quality":"ORG","year":"2024","rating":"","source":"fojik","url":"https://fojik.com/movie/witchboard-2024/"},{"id":"kitab-sijjin-illiyyin-the-book-of-sijjin-illiyyin","slug":"kitab-sijjin-illiyyin-the-book-of-sijjin-illiyyin","title":"Kitab Sijjin & Illiyyin – The Book of Sijjin & Illiyyin (2025) Indonesian WEB-DL 480p, 720p & 1080p | GDRive | ESub","poster":"https://fojik.com/wp-content/uploads/5c8iXGH5Vol8HfpdwXK5ptHKQ6R.jpg","quality":"WEB-DL","year":"2025","rating":"","source":"fojik","url":"https://fojik.com/movie/kitab-sijjin-illiyyin-the-book-of-sijjin-illiyyin/"},{"id":"hellraiser-2022","slug":"hellraiser-2022","title":"Hellraiser (2022) Dual Audio [Hindi ORG & ENG] WEB-DL 480p, 720p & 1080p | GDRive","poster":"https://fojik.com/wp-content/uploads/t5LNhr1cBYEliNkVUy1LHdV2aLe.jpg","quality":"ORG","year":"2022","rating":"","source":"fojik","url":"https://fojik.com/movie/hellraiser-2022/"},{"id":"five-nights-at-freddys-2-2025","slug":"five-nights-at-freddys-2-2025","title":"Five Nights at Freddy’s 2 (2025) Dual Audio [Hindi ORG & ENG] WEB-DL 480p, 720p & 1080p | GDRive","poster":"https://fojik.com/wp-content/uploads/udAxQEORq2I5wxI97N2TEqdhzBE.jpg","quality":"ORG","year":"2025","rating":"","source":"fojik","url":"https://fojik.com/movie/five-nights-at-freddys-2-2025/"},{"id":"it-welcome-to-derry","slug":"it-welcome-to-derry","title":"It: Welcome to Derry : Season 1 Dual Audio [Hindi ORG & ENG] WEB-DL 720p & 1080p HEVC | [Epi 1-8 All Added – Complete Zip Batch Added]","poster":"https://fojik.com/wp-content/uploads/sa26OBVEYzYRButAGkMlwr3rTkB.jpg","quality":"ORG","year":"","rating":"","source":"fojik","url":"https://fojik.com/movie/it-welcome-to-derry/"},{"id":"last-the-night-2022","slug":"last-the-night-2022","title":"Last the Night (2022) Dual Audio [Hindi ORG & ENG] WEB-DL 480p, 720p & 1080p | GDRive","poster":"https://fojik.com/wp-content/uploads/4ansctfgMbWWWUgVVJOFtAZYEJA.jpg","quality":"ORG","year":"2022","rating":"","source":"fojik","url":"https://fojik.com/movie/last-the-night-2022/"},{"id":"angels-fallen-warriors-of-peace-2024","slug":"angels-fallen-warriors-of-peace-2024","title":"Angels Fallen: Warriors of Peace (2024) Dual Audio [Hindi ORG & ENG] WEB-DL 480p, 720p & 1080p | GDRive","poster":"https://fojik.com/wp-content/uploads/5J0tYPI8pM6rQdUdHea0zUwLlK2.jpg","quality":"ORG","year":"2024","rating":"","source":"fojik","url":"https://fojik.com/movie/angels-fallen-warriors-of-peace-2024/"},{"id":"operation-undead-2024","slug":"operation-undead-2024","title":"Operation Undead (2024) Dual Audio [Hindi ORG & Thai] WEB-DL 480p, 720p & 1080p | GDRive","poster":"https://fojik.com/wp-content/uploads/rs10lMBnJFnJX1Y7MYpyB8JiNAF.jpg","quality":"ORG","year":"2024","rating":"","source":"fojik","url":"https://fojik.com/movie/operation-undead-2024/"},{"id":"the-returning-dead-selepas-tahlil","slug":"the-returning-dead-selepas-tahlil","title":"The Returning Dead – Selepas Tahlil (2025) Indonesian WEB-DL 480p, 720p & 1080p | GDRive | ESub","poster":"https://fojik.com/wp-content/uploads/7rRdMUnLAEAE5JUuOfWqWjoC3xs.jpg","quality":"WEB-DL","year":"2025","rating":"","source":"fojik","url":"https://fojik.com/movie/the-returning-dead-selepas-tahlil/"},{"id":"the-night","slug":"the-night","title":"The Night (2020) Dual Audio [Hindi ORG & Persian] WEB-DL 480p, 720p & 1080p | GDRive","poster":"https://fojik.com/wp-content/uploads/d7iycGAm02vlKPGSjYOHzm9U7JF.jpg","quality":"ORG","year":"2020","rating":"","source":"fojik","url":"https://fojik.com/movie/the-night/"},{"id":"urban-myths-2022-web-dl-480p-720p-1080p-gdrive","slug":"urban-myths-2022-web-dl-480p-720p-1080p-gdrive","title":"Urban Myths (2022) Dual Audio [Hindi ORG & Korean] WEB-DL 480p, 720p & 1080p | GDRive","poster":"https://fojik.com/wp-content/uploads/2ZWxZvDWYoDj7PHFizgi17yEZyb.jpg","quality":"ORG","year":"2022","rating":"","source":"fojik","url":"https://fojik.com/movie/urban-myths-2022-web-dl-480p-720p-1080p-gdrive/"},{"id":"moloch-2022-web-dl-480p-720p-1080p-gdrive","slug":"moloch-2022-web-dl-480p-720p-1080p-gdrive","title":"Moloch (2022) Dual Audio [Hindi ORG & Dutch] WEB-DL 480p, 720p & 1080p | GDRive","poster":"https://fojik.com/wp-content/uploads/3jVzYOnylmvo7ZnGerjfoRj2wFz.jpg","quality":"ORG","year":"2022","rating":"","source":"fojik","url":"https://fojik.com/movie/moloch-2022-web-dl-480p-720p-1080p-gdrive/"},{"id":"sound-of-silence-2023","slug":"sound-of-silence-2023","title":"Sound of Silence (2023) Dual Audio [Hindi ORG & ENG] WEB-DL 480p, 720p & 1080p | GDRive","poster":"https://fojik.com/wp-content/uploads/jiQbiEs7yPVPHzCp0Bn9UH83Tq0.jpg","quality":"ORG","year":"2023","rating":"","source":"fojik","url":"https://fojik.com/movie/sound-of-silence-2023/"},{"id":"black-phone-2-2025","slug":"black-phone-2-2025","title":"Black Phone 2 (2025) Dual Audio [Hindi ORG & ENG] WEB-DL 480p, 720p & 1080p | GDRive","poster":"https://fojik.com/wp-content/uploads/d9kDYFoQzcmhWtmncJhKsFq8KoH.jpg","quality":"ORG","year":"2025","rating":"","source":"fojik","url":"https://fojik.com/movie/black-phone-2-2025/"},{"id":"bambi-the-reckoning-2025-web-dl-480p-720p-1080p-gdrive","slug":"bambi-the-reckoning-2025-web-dl-480p-720p-1080p-gdrive","title":"Bambi: The Reckoning (2025) Dual Audio [Hindi ORG & ENG] WEB-DL 480p, 720p & 1080p | GDRive","poster":"https://fojik.com/wp-content/uploads/wj109zNCYvMf3i9l23vEHL98IAP.jpg","quality":"ORG","year":"2025","rating":"","source":"fojik","url":"https://fojik.com/movie/bambi-the-reckoning-2025-web-dl-480p-720p-1080p-gdrive/"},{"id":"dark-nuns-2025","slug":"dark-nuns-2025","title":"Dark Nuns (2025) Dual Audio [Hindi ORG & Korean] WEB-DL 480p, 720p & 1080p | GDRive","poster":"https://fojik.com/wp-content/uploads/xgwOZpnA8vRRvVewCb7WYnfwMfo.jpg","quality":"ORG","year":"2025","rating":"","source":"fojik","url":"https://fojik.com/movie/dark-nuns-2025/"},{"id":"maxxxine-2024","slug":"maxxxine-2024","title":"MaXXXine (2024) Dual Audio [Hindi ORG & ENG] WEB-DL 480p, 720p & 1080p | GDRive","poster":"https://fojik.com/wp-content/uploads/Image-27-3.png","quality":"ORG","year":"2024","rating":"","source":"fojik","url":"https://fojik.com/movie/maxxxine-2024/"},{"id":"monster-summer-2024-web-dl-480p-720p-1080p-gdrive","slug":"monster-summer-2024-web-dl-480p-720p-1080p-gdrive","title":"Monster Summer (2024) Dual Audio [Hindi ORG & ENG] WEB-DL 480p, 720p & 1080p | GDRive","poster":"https://fojik.com/wp-content/uploads/zD2UZkh0DwbDEMuOKIR7jgwgulZ.jpg","quality":"ORG","year":"2024","rating":"","source":"fojik","url":"https://fojik.com/movie/monster-summer-2024-web-dl-480p-720p-1080p-gdrive/"},{"id":"the-elixir-2025-web-dl-480p-720p-1080p-gdrive","slug":"the-elixir-2025-web-dl-480p-720p-1080p-gdrive","title":"The Elixir (2025) Dual Audio [Hindi ORG & ENG] WEB-DL 480p, 720p & 1080p | GDRive","poster":"https://fojik.com/wp-content/uploads/hQYEkXiAcgzQkr4aqLxWpNUFvN5.jpg","quality":"ORG","year":"2025","rating":"","source":"fojik","url":"https://fojik.com/movie/the-elixir-2025-web-dl-480p-720p-1080p-gdrive/"},{"id":"the-jester-2-2025-web-dl-480p-720p-1080p-gdrive","slug":"the-jester-2-2025-web-dl-480p-720p-1080p-gdrive","title":"The Jester 2 (2025) Dual Audio [Hindi ORG & ENG] WEB-DL 480p, 720p & 1080p | GDRive","poster":"https://fojik.site/wp-content/uploads/giV7FS7HGyxRbwqxudXPvv1RgXD.jpg","quality":"ORG","year":"2025","rating":"","source":"fojik","url":"https://fojik.site/movie/the-jester-2-2025-web-dl-480p-720p-1080p-gdrive/"}],"hasMore":true,"source":"fojik","ts":1784798648455}