{"ok":true,"page":157,"totalPages":186,"items":[{"id":"?attachment_id=38288","slug":"?attachment_id=38288","title":"?Attachment_id=38288","poster":"https://fojik.site/wp-content/uploads/?attachment_id=38288.jpg","quality":"HD","year":"","rating":"","source":"fojik","url":"https://fojik.site/movie/?attachment_id=38288/"},{"id":"adspic-3","slug":"adspic-3","title":"Adspic 3","poster":"https://fojik.site/wp-content/uploads/adspic-3.jpg","quality":"HD","year":"","rating":"","source":"fojik","url":"https://fojik.site/movie/adspic-3/"},{"id":"sosgvos2rfnrw0zn5w7laosmqgc-jpg","slug":"sosgvos2rfnrw0zn5w7laosmqgc-jpg","title":"Sosgvos2rfnrw0zn5w7laosmqgc Jpg","poster":"https://fojik.site/wp-content/uploads/sosgvos2rfnrw0zn5w7laosmqgc-jpg.jpg","quality":"HD","year":"","rating":"","source":"fojik","url":"https://fojik.site/movie/sosgvos2rfnrw0zn5w7laosmqgc-jpg/"},{"id":"ufo2j8fupwwtm2kj7zuaqhxmuuk-jpg","slug":"ufo2j8fupwwtm2kj7zuaqhxmuuk-jpg","title":"Ufo2j8fupwwtm2kj7zuaqhxmuuk Jpg","poster":"https://fojik.site/wp-content/uploads/ufo2j8fupwwtm2kj7zuaqhxmuuk-jpg.jpg","quality":"HD","year":"","rating":"","source":"fojik","url":"https://fojik.site/movie/ufo2j8fupwwtm2kj7zuaqhxmuuk-jpg/"},{"id":"owul2s2dqbz0hi7psqf94weyr0q-jpg","slug":"owul2s2dqbz0hi7psqf94weyr0q-jpg","title":"Owul2s2dqbz0hi7psqf94weyr0q Jpg","poster":"https://fojik.site/wp-content/uploads/owul2s2dqbz0hi7psqf94weyr0q-jpg.jpg","quality":"HD","year":"","rating":"","source":"fojik","url":"https://fojik.site/movie/owul2s2dqbz0hi7psqf94weyr0q-jpg/"},{"id":"30jdkqadkcmm7wme54c7yi1qxfs-jpg","slug":"30jdkqadkcmm7wme54c7yi1qxfs-jpg","title":"30jdkqadkcmm7wme54c7yi1qxfs Jpg","poster":"https://fojik.site/wp-content/uploads/30jdkqadkcmm7wme54c7yi1qxfs-jpg.jpg","quality":"HD","year":"","rating":"","source":"fojik","url":"https://fojik.site/movie/30jdkqadkcmm7wme54c7yi1qxfs-jpg/"},{"id":"k2eilncmmpgkf2y0dhhora7cb3-jpg","slug":"k2eilncmmpgkf2y0dhhora7cb3-jpg","title":"K2eilncmmpgkf2y0dhhora7cb3 Jpg","poster":"https://fojik.site/wp-content/uploads/k2eilncmmpgkf2y0dhhora7cb3-jpg.jpg","quality":"HD","year":"","rating":"","source":"fojik","url":"https://fojik.site/movie/k2eilncmmpgkf2y0dhhora7cb3-jpg/"},{"id":"2fyf5x8ox0nthoity4iqigw6hgw-jpg","slug":"2fyf5x8ox0nthoity4iqigw6hgw-jpg","title":"2fyf5x8ox0nthoity4iqigw6hgw Jpg","poster":"https://fojik.site/wp-content/uploads/2fyf5x8ox0nthoity4iqigw6hgw-jpg.jpg","quality":"HD","year":"","rating":"","source":"fojik","url":"https://fojik.site/movie/2fyf5x8ox0nthoity4iqigw6hgw-jpg/"},{"id":"2zzbc4bodopujmzbx6klladi0rw-jpg","slug":"2zzbc4bodopujmzbx6klladi0rw-jpg","title":"2zzbc4bodopujmzbx6klladi0rw Jpg","poster":"https://fojik.site/wp-content/uploads/2zzbc4bodopujmzbx6klladi0rw-jpg.jpg","quality":"HD","year":"","rating":"","source":"fojik","url":"https://fojik.site/movie/2zzbc4bodopujmzbx6klladi0rw-jpg/"},{"id":"?attachment_id=38115","slug":"?attachment_id=38115","title":"?Attachment_id=38115","poster":"https://fojik.site/wp-content/uploads/?attachment_id=38115.jpg","quality":"HD","year":"","rating":"","source":"fojik","url":"https://fojik.site/movie/?attachment_id=38115/"},{"id":"k4s7mmhndfrkfmsnc0sm1ripezu-jpg","slug":"k4s7mmhndfrkfmsnc0sm1ripezu-jpg","title":"K4s7mmhndfrkfmsnc0sm1ripezu Jpg","poster":"https://fojik.site/wp-content/uploads/k4s7mmhndfrkfmsnc0sm1ripezu-jpg.jpg","quality":"HD","year":"","rating":"","source":"fojik","url":"https://fojik.site/movie/k4s7mmhndfrkfmsnc0sm1ripezu-jpg/"},{"id":"94gn5ddcttsyb34aqu2tqq6fx8u-jpg","slug":"94gn5ddcttsyb34aqu2tqq6fx8u-jpg","title":"94gn5ddcttsyb34aqu2tqq6fx8u Jpg","poster":"https://fojik.site/wp-content/uploads/94gn5ddcttsyb34aqu2tqq6fx8u-jpg.jpg","quality":"HD","year":"","rating":"","source":"fojik","url":"https://fojik.site/movie/94gn5ddcttsyb34aqu2tqq6fx8u-jpg/"},{"id":"dd3hcmczlc9wnvfnzx4pzvyl6q8-jpg-2","slug":"dd3hcmczlc9wnvfnzx4pzvyl6q8-jpg-2","title":"Dd3hcmczlc9wnvfnzx4pzvyl6q8 Jpg 2","poster":"https://fojik.site/wp-content/uploads/dd3hcmczlc9wnvfnzx4pzvyl6q8-jpg-2.jpg","quality":"HD","year":"","rating":"","source":"fojik","url":"https://fojik.site/movie/dd3hcmczlc9wnvfnzx4pzvyl6q8-jpg-2/"},{"id":"dd3hcmczlc9wnvfnzx4pzvyl6q8-jpg","slug":"dd3hcmczlc9wnvfnzx4pzvyl6q8-jpg","title":"Dd3hcmczlc9wnvfnzx4pzvyl6q8 Jpg","poster":"https://fojik.site/wp-content/uploads/dd3hcmczlc9wnvfnzx4pzvyl6q8-jpg.jpg","quality":"HD","year":"","rating":"","source":"fojik","url":"https://fojik.site/movie/dd3hcmczlc9wnvfnzx4pzvyl6q8-jpg/"},{"id":"38101","slug":"38101","title":"38101","poster":"https://fojik.site/wp-content/uploads/38101.jpg","quality":"HD","year":"","rating":"","source":"fojik","url":"https://fojik.site/movie/38101/"},{"id":"khs0dgapwromrprpgzcurek2kjt-jpg","slug":"khs0dgapwromrprpgzcurek2kjt-jpg","title":"Khs0dgapwromrprpgzcurek2kjt Jpg","poster":"https://fojik.site/wp-content/uploads/khs0dgapwromrprpgzcurek2kjt-jpg.jpg","quality":"HD","year":"","rating":"","source":"fojik","url":"https://fojik.site/movie/khs0dgapwromrprpgzcurek2kjt-jpg/"},{"id":"or06fn3dka5tukk1e9sl16pb3iy-jpg-6","slug":"or06fn3dka5tukk1e9sl16pb3iy-jpg-6","title":"Or06fn3dka5tukk1e9sl16pb3iy Jpg 6","poster":"https://fojik.site/wp-content/uploads/or06fn3dka5tukk1e9sl16pb3iy-jpg-6.jpg","quality":"HD","year":"","rating":"","source":"fojik","url":"https://fojik.site/movie/or06fn3dka5tukk1e9sl16pb3iy-jpg-6/"},{"id":"uiv460nxqx8t5fjwemgfops6dgh-jpg","slug":"uiv460nxqx8t5fjwemgfops6dgh-jpg","title":"Uiv460nxqx8t5fjwemgfops6dgh Jpg","poster":"https://fojik.site/wp-content/uploads/uiv460nxqx8t5fjwemgfops6dgh-jpg.jpg","quality":"HD","year":"","rating":"","source":"fojik","url":"https://fojik.site/movie/uiv460nxqx8t5fjwemgfops6dgh-jpg/"},{"id":"trdbxpbpiburn6gyjnxstyksilv-jpg","slug":"trdbxpbpiburn6gyjnxstyksilv-jpg","title":"Trdbxpbpiburn6gyjnxstyksilv Jpg","poster":"https://fojik.site/wp-content/uploads/trdbxpbpiburn6gyjnxstyksilv-jpg.jpg","quality":"HD","year":"","rating":"","source":"fojik","url":"https://fojik.site/movie/trdbxpbpiburn6gyjnxstyksilv-jpg/"},{"id":"suhtgtq4wjeejvosvnzcplh8sep-jpg","slug":"suhtgtq4wjeejvosvnzcplh8sep-jpg","title":"Suhtgtq4wjeejvosvnzcplh8sep Jpg","poster":"https://fojik.site/wp-content/uploads/suhtgtq4wjeejvosvnzcplh8sep-jpg.jpg","quality":"HD","year":"","rating":"","source":"fojik","url":"https://fojik.site/movie/suhtgtq4wjeejvosvnzcplh8sep-jpg/"}],"hasMore":true,"source":"fojik","ts":1784798648488}